{
  "date": "2026-05-31",
  "generated_at": "2026-06-29T23:13:30.351450",
  "count": 31,
  "entries": [
    {
      "fixture_id": 1518096,
      "strategy": "lay_zebrao",
      "league": "V.League 1",
      "league_id": 340,
      "league_country": "Vietnam",
      "league_logo": "https://media.api-sports.io/football/leagues/340.png",
      "date": "2026-05-31",
      "time": "08:00",
      "venue": "Hang Day Stadium",
      "home_team": "Công An Nhân Dân",
      "home_team_id": 16400,
      "home_team_logo": "https://media.api-sports.io/football/teams/16400.png",
      "away_team": "Binh Duong",
      "away_team_id": 3668,
      "away_team_logo": "https://media.api-sports.io/football/teams/3668.png",
      "favorite_side": "home",
      "favorite": "Công An Nhân Dân",
      "underdog": "Binh Duong",
      "odds": {
        "home_win": 1.1663636363636363,
        "draw": 6.896363636363637,
        "away_win": 9.742727272727272,
        "score_1x0": 11.536249999999999,
        "score_0x1": 38.66,
        "over25": 1.2285714285714284,
        "btts_yes": 1.6224999999999998,
        "prob_1x0": 8.7,
        "prob_0x1": 2.6,
        "short_score_risk": 11.3,
        "favorite_odd": 1.1663636363636363,
        "best_goleada_odd": 7.914999999999999
      },
      "home_stats": {
        "rank": 3,
        "goals_avg": 2.4,
        "goals_conceded_avg": 0.8,
        "over25_pct": 50.0,
        "btts_pct": 60.0,
        "draw_pct": 20.0,
        "form": "WDWWW",
        "offensive_strength": 1.85,
        "defensive_fragility": 0.62,
        "avg_shots_on_goal": 0.0,
        "avg_possession": 0.0,
        "avg_corners": 0.0,
        "pressure_index": 0.0,
        "win_pct": 80.0
      },
      "away_stats": {
        "rank": 7,
        "goals_avg": 1.1,
        "goals_conceded_avg": 1.8,
        "over25_pct": 40.0,
        "btts_pct": 70.0,
        "draw_pct": 30.0,
        "form": "LLLLD",
        "offensive_strength": 0.85,
        "defensive_fragility": 1.38,
        "avg_shots_on_goal": 0.0,
        "avg_possession": 0.0,
        "avg_corners": 0.0,
        "pressure_index": 0.0,
        "win_pct": 10.0
      },
      "score": 82.4,
      "score_class": "FORTE",
      "market": "LAY ZEBRÃO",
      "justification": "Công An Nhân Dân ataque 2.4, Over2.5 50% — zebra (Binh Duong) odd 9.74, sofre 1.8/j",
      "risk_note": "Operação in-play: sair em 0-0 HT, gol da zebra ou red. Seguir se favorito marcar primeiro. PnL informado manualmente.",
      "passed_filters": true,
      "filter_rejections": [],
      "stage": "operation",
      "status": "breakeven",
      "final_score": "manual",
      "pnl": 0.0,
      "resistance_index": 0.0,
      "lay_stake": 1000.0,
      "fair_odd": 39.14,
      "prob_lose_pct": 2.56,
      "fair_note": "xG 3.14/0.90 | calibrado c/ O2.5 | P(avg 1x0/0x1) | mercado score_0x1 → 2.2% | blend 55/45",
      "manual_pnl": 0.0
    },
    {
      "fixture_id": 1518096,
      "strategy": "over_15",
      "league": "V.League 1",
      "league_id": 340,
      "league_country": "Vietnam",
      "league_logo": "https://media.api-sports.io/football/leagues/340.png",
      "date": "2026-05-31",
      "time": "08:00",
      "venue": "Hang Day Stadium",
      "home_team": "Công An Nhân Dân",
      "home_team_id": 16400,
      "home_team_logo": "https://media.api-sports.io/football/teams/16400.png",
      "away_team": "Binh Duong",
      "away_team_id": 3668,
      "away_team_logo": "https://media.api-sports.io/football/teams/3668.png",
      "favorite_side": "home",
      "favorite": "Công An Nhân Dân",
      "underdog": "Binh Duong",
      "odds": {
        "home_win": 1.1663636363636363,
        "draw": 6.896363636363637,
        "away_win": 9.742727272727272,
        "score_1x0": 11.536249999999999,
        "score_0x1": 38.66,
        "over25": 1.2285714285714284,
        "btts_yes": 1.6224999999999998,
        "prob_1x0": 8.7,
        "prob_0x1": 2.6,
        "short_score_risk": 11.3,
        "favorite_odd": 1.1663636363636363,
        "best_goleada_odd": 7.914999999999999
      },
      "home_stats": {
        "rank": 3,
        "goals_avg": 2.4,
        "goals_conceded_avg": 0.8,
        "over25_pct": 50.0,
        "over15_pct": 90.0,
        "goals_scored_home_avg": 3.2,
        "goals_scored_away_avg": 1.6,
        "goals_conceded_home_avg": 1.2,
        "goals_conceded_away_avg": 0.4,
        "scored_in_home_pct": 100.0,
        "scored_in_away_pct": 100.0,
        "conceded_in_home_pct": 80.0,
        "conceded_in_away_pct": 40.0,
        "over15_home_pct": 100.0,
        "over15_away_pct": 80.0,
        "btts_pct": 60.0,
        "draw_pct": 20.0,
        "form": "WDWWW",
        "offensive_strength": 1.85,
        "defensive_fragility": 0.62,
        "avg_shots_on_goal": 0.0,
        "avg_possession": 0.0,
        "avg_corners": 0.0,
        "pressure_index": 0.0,
        "win_pct": 80.0
      },
      "away_stats": {
        "rank": 7,
        "goals_avg": 1.1,
        "goals_conceded_avg": 1.8,
        "over25_pct": 40.0,
        "over15_pct": 90.0,
        "goals_scored_home_avg": 1.0,
        "goals_scored_away_avg": 1.2,
        "goals_conceded_home_avg": 1.0,
        "goals_conceded_away_avg": 2.6,
        "scored_in_home_pct": 80.0,
        "scored_in_away_pct": 80.0,
        "conceded_in_home_pct": 80.0,
        "conceded_in_away_pct": 100.0,
        "over15_home_pct": 80.0,
        "over15_away_pct": 100.0,
        "btts_pct": 70.0,
        "draw_pct": 30.0,
        "form": "LLLLD",
        "offensive_strength": 0.85,
        "defensive_fragility": 1.38,
        "avg_shots_on_goal": 0.0,
        "avg_possession": 0.0,
        "avg_corners": 0.0,
        "pressure_index": 0.0,
        "win_pct": 10.0
      },
      "score": 76.8,
      "score_class": "FORTE",
      "market": "OVER 1.5",
      "justification": "Média Gols: 3.50; Over 1.5 geral médio: 90.0%; Casa marca em casa: 100.0%; Fora marca fora: 80.0%",
      "risk_note": "Ganhamos com 2+ gols totais na partida. BTTS geral médio: 65.0%.",
      "passed_filters": true,
      "filter_rejections": [],
      "stage": "rejected_by_odd",
      "status": "pending",
      "final_score": "",
      "pnl": 0.0,
      "resistance_index": 0.0,
      "recommended_odd": 1.49,
      "league_avg_goals": 2.47,
      "league_edge_pct": -13.3,
      "fair_odd": 1.09,
      "prob_lose_pct": 92.0,
      "fair_note": "xG 3.14/0.90 | calibrado c/ O2.5 | Poisson P(Over 1.5) | mercado Over 1.5 proxy → 92.1% | P(Over 1.5) | blend 55/45",
      "manual_odd": 50.0,
      "reject_reason": "Odd Lay muito alta para over_15 (50.0 > 25.0)",
      "ev_pct": 4500.0
    },
    {
      "fixture_id": 1546288,
      "strategy": "over_15",
      "league": "Czech Liga",
      "league_id": 345,
      "league_country": "Czech-Republic",
      "league_logo": "https://media.api-sports.io/football/leagues/345.png",
      "date": "2026-05-31",
      "time": "08:00",
      "venue": "Mestsky Fotbalovy Stadion",
      "home_team": "Slovácko",
      "home_team_id": 3719,
      "home_team_logo": "https://media.api-sports.io/football/teams/3719.png",
      "away_team": "Artis",
      "away_team_id": 4257,
      "away_team_logo": "https://media.api-sports.io/football/teams/4257.png",
      "favorite_side": "home",
      "favorite": "Slovácko",
      "underdog": "Artis",
      "odds": {
        "home_win": 1.4916666666666665,
        "draw": 4.256666666666667,
        "away_win": 5.549166666666667,
        "score_1x0": 7.655555555555556,
        "score_0x1": 16.040000000000003,
        "over25": 1.5750000000000002,
        "btts_yes": 1.6824999999999999,
        "prob_1x0": 13.1,
        "prob_0x1": 6.2,
        "short_score_risk": 19.3,
        "favorite_odd": 1.4916666666666665,
        "best_goleada_odd": 10.652222222222223
      },
      "home_stats": {
        "rank": 4,
        "goals_avg": 1.4,
        "goals_conceded_avg": 1.4,
        "over25_pct": 70.0,
        "over15_pct": 80.0,
        "goals_scored_home_avg": 1.4,
        "goals_scored_away_avg": 1.4,
        "goals_conceded_home_avg": 1.8,
        "goals_conceded_away_avg": 1.0,
        "scored_in_home_pct": 80.0,
        "scored_in_away_pct": 80.0,
        "conceded_in_home_pct": 80.0,
        "conceded_in_away_pct": 80.0,
        "over15_home_pct": 100.0,
        "over15_away_pct": 60.0,
        "btts_pct": 60.0,
        "draw_pct": 10.0,
        "form": "WWLLW",
        "offensive_strength": 1.08,
        "defensive_fragility": 1.08,
        "avg_shots_on_goal": 5.2,
        "avg_possession": 64.0,
        "avg_corners": 4.8,
        "pressure_index": 98.8,
        "win_pct": 40.0
      },
      "away_stats": {
        "rank": null,
        "goals_avg": 1.6,
        "goals_conceded_avg": 1.6,
        "over25_pct": 60.0,
        "over15_pct": 100.0,
        "goals_scored_home_avg": 1.8,
        "goals_scored_away_avg": 1.4,
        "goals_conceded_home_avg": 1.8,
        "goals_conceded_away_avg": 1.4,
        "scored_in_home_pct": 80.0,
        "scored_in_away_pct": 80.0,
        "conceded_in_home_pct": 100.0,
        "conceded_in_away_pct": 80.0,
        "over15_home_pct": 100.0,
        "over15_away_pct": 100.0,
        "btts_pct": 70.0,
        "draw_pct": 20.0,
        "form": "LLLWW",
        "offensive_strength": 1.23,
        "defensive_fragility": 1.23,
        "avg_shots_on_goal": 2.0,
        "avg_possession": 30.5,
        "avg_corners": 5.5,
        "pressure_index": 9.0,
        "win_pct": 40.0
      },
      "score": 74.8,
      "score_class": "BOA",
      "market": "OVER 1.5",
      "justification": "Média Gols: 3.00; Over 1.5 geral médio: 90.0%; Casa marca em casa: 80.0%; Fora marca fora: 80.0%",
      "risk_note": "Ganhamos com 2+ gols totais na partida. BTTS geral médio: 65.0%.",
      "passed_filters": true,
      "filter_rejections": [],
      "stage": "rejected_by_odd",
      "status": "pending",
      "final_score": "",
      "pnl": 0.0,
      "resistance_index": 0.0,
      "recommended_odd": 1.42,
      "league_avg_goals": 2.63,
      "league_edge_pct": 16.3,
      "fair_odd": 1.28,
      "prob_lose_pct": 78.08,
      "fair_note": "xG 1.71/1.40 | calibrado c/ O2.5 | Poisson P(Over 1.5) | mercado Over 1.5 proxy → 71.9% | P(Over 1.5) | blend 55/45",
      "manual_odd": 50.0,
      "reject_reason": "Odd Lay muito alta para over_15 (50.0 > 25.0)",
      "ev_pct": 3804.0
    },
    {
      "fixture_id": 1546288,
      "strategy": "lay_zebra",
      "league": "Czech Liga",
      "league_id": 345,
      "league_country": "Czech-Republic",
      "league_logo": "https://media.api-sports.io/football/leagues/345.png",
      "date": "2026-05-31",
      "time": "08:00",
      "venue": "Mestsky Fotbalovy Stadion",
      "home_team": "Slovácko",
      "home_team_id": 3719,
      "home_team_logo": "https://media.api-sports.io/football/teams/3719.png",
      "away_team": "Artis",
      "away_team_id": 4257,
      "away_team_logo": "https://media.api-sports.io/football/teams/4257.png",
      "favorite_side": "home",
      "favorite": "Slovácko",
      "underdog": "Artis",
      "odds": {
        "home_win": 1.4916666666666665,
        "draw": 4.256666666666667,
        "away_win": 5.549166666666667,
        "score_1x0": 7.655555555555556,
        "score_0x1": 16.040000000000003,
        "over25": 1.5750000000000002,
        "btts_yes": 1.6824999999999999,
        "prob_1x0": 13.1,
        "prob_0x1": 6.2,
        "short_score_risk": 19.3,
        "favorite_odd": 1.4916666666666665,
        "best_goleada_odd": 10.652222222222223
      },
      "home_stats": {
        "rank": 4,
        "goals_avg": 1.4,
        "goals_conceded_avg": 1.4,
        "over25_pct": 70.0,
        "btts_pct": 60.0,
        "draw_pct": 10.0,
        "form": "WWLLW",
        "offensive_strength": 1.08,
        "defensive_fragility": 1.08,
        "avg_shots_on_goal": 5.2,
        "avg_possession": 64.0,
        "avg_corners": 4.8,
        "pressure_index": 98.8,
        "win_pct": 40.0
      },
      "away_stats": {
        "rank": null,
        "goals_avg": 1.6,
        "goals_conceded_avg": 1.6,
        "over25_pct": 60.0,
        "btts_pct": 70.0,
        "draw_pct": 20.0,
        "form": "LLLWW",
        "offensive_strength": 1.23,
        "defensive_fragility": 1.23,
        "avg_shots_on_goal": 2.0,
        "avg_possession": 30.5,
        "avg_corners": 5.5,
        "pressure_index": 9.0,
        "win_pct": 40.0
      },
      "score": 68.6,
      "score_class": "BOA",
      "market": "LAY ZEBRA",
      "justification": "Análise: Slovácko em boa fase (9/15 pts); Artis raramente vence (40% vitórias). Probabilidade de Zebra é baixa.",
      "risk_note": "Lembre-se: Ganhamos no Empate ou Vitória do Favorito. Perigo apenas se a Zebra vencer.",
      "passed_filters": true,
      "filter_rejections": [],
      "stage": "operation",
      "status": "green",
      "final_score": "3x0",
      "pnl": 149.22,
      "resistance_index": 0.0,
      "fair_odd": 18.54,
      "prob_lose_pct": 5.39,
      "fair_note": "xG 1.71/1.40 | calibrado c/ O2.5 | P(avg 1x0/0x1) | mercado score_0x1 → 5.4% | blend 55/45",
      "manual_odd": 7.4,
      "lay_stake": 156.25,
      "lay_profit_green": 149.22,
      "lay_loss_red": -1000.0,
      "ev_pct": 60.11
    },
    {
      "fixture_id": 1494192,
      "strategy": "back_btts",
      "league": "Allsvenskan",
      "league_id": 113,
      "league_country": "Sweden",
      "league_logo": "https://media.api-sports.io/football/leagues/113.png",
      "date": "2026-05-31",
      "time": "09:00",
      "venue": "Hitachi Energy Arena",
      "home_team": "Vasteras SK FK",
      "home_team_id": 2241,
      "home_team_logo": "https://media.api-sports.io/football/teams/2241.png",
      "away_team": "IFK Goteborg",
      "away_team_id": 366,
      "away_team_logo": "https://media.api-sports.io/football/teams/366.png",
      "favorite_side": "away",
      "favorite": "IFK Goteborg",
      "underdog": "Vasteras SK FK",
      "odds": {
        "home_win": 2.61,
        "draw": 3.3200000000000003,
        "away_win": 2.5775,
        "score_1x0": 8.518,
        "score_0x1": 8.439,
        "over25": 1.888,
        "btts_yes": 1.6688888888888889,
        "prob_1x0": 11.7,
        "prob_0x1": 11.8,
        "short_score_risk": 23.6,
        "favorite_odd": 2.5775,
        "best_goleada_odd": 18.816
      },
      "home_stats": {
        "rank": null,
        "goals_avg": 1.8,
        "goals_conceded_avg": 2.5,
        "over25_pct": 80.0,
        "over15_pct": 90.0,
        "goals_scored_home_avg": 2.0,
        "goals_scored_away_avg": 1.6,
        "goals_conceded_home_avg": 2.4,
        "goals_conceded_away_avg": 2.6,
        "scored_in_home_pct": 80.0,
        "scored_in_away_pct": 80.0,
        "conceded_in_home_pct": 100.0,
        "conceded_in_away_pct": 100.0,
        "over15_home_pct": 80.0,
        "over15_away_pct": 100.0,
        "btts_pct": 80.0,
        "draw_pct": 30.0,
        "form": "LLWDL",
        "offensive_strength": 1.38,
        "defensive_fragility": 1.92,
        "avg_shots_on_goal": 3.5,
        "avg_possession": 52.8,
        "avg_corners": 4.2,
        "pressure_index": 60.5,
        "win_pct": 20.0
      },
      "away_stats": {
        "rank": 4,
        "goals_avg": 1.5,
        "goals_conceded_avg": 2.1,
        "over25_pct": 50.0,
        "over15_pct": 90.0,
        "goals_scored_home_avg": 1.0,
        "goals_scored_away_avg": 2.0,
        "goals_conceded_home_avg": 1.4,
        "goals_conceded_away_avg": 2.8,
        "scored_in_home_pct": 80.0,
        "scored_in_away_pct": 80.0,
        "conceded_in_home_pct": 100.0,
        "conceded_in_away_pct": 100.0,
        "over15_home_pct": 80.0,
        "over15_away_pct": 100.0,
        "btts_pct": 80.0,
        "draw_pct": 50.0,
        "form": "LDWDW",
        "offensive_strength": 1.15,
        "defensive_fragility": 1.62,
        "avg_shots_on_goal": 7.3,
        "avg_possession": 47.3,
        "avg_corners": 3.7,
        "pressure_index": 78.0,
        "win_pct": 20.0
      },
      "score": 98.4,
      "score_class": "ELITE",
      "market": "BACK BTTS",
      "justification": "BTTS médio 80%; Vasteras SK FK marca em casa 80%, IFK Goteborg marca fora 80%; odd BTTS 1.67",
      "risk_note": "Perde se qualquer time zerar. Casa sofre em casa 100%, Fora sofre fora 100%.",
      "passed_filters": true,
      "filter_rejections": [],
      "stage": "rejected_by_odd",
      "status": "pending",
      "final_score": "",
      "pnl": 0.0,
      "resistance_index": 0.0,
      "recommended_odd": 0.0,
      "league_avg_goals": 0.0,
      "league_edge_pct": 0.0,
      "fair_odd": 1.43,
      "prob_lose_pct": 69.96,
      "fair_note": "xG 2.50/2.06 | Poisson+DC P(BTTS) | mercado BTTS Sim → 56.5% | P(BTTS Sim) | blend 55/45",
      "manual_odd": 50.0,
      "reject_reason": "Odd Lay muito alta para back_btts (50.0 > 25.0)",
      "ev_pct": 3398.0
    },
    {
      "fixture_id": 1538264,
      "strategy": "lay_zebra",
      "league": "1. Division",
      "league_id": 120,
      "league_country": "Denmark",
      "league_logo": "https://media.api-sports.io/football/leagues/120.png",
      "date": "2026-05-31",
      "time": "10:00",
      "venue": "Hybel Arena Horsens",
      "home_team": "AC Horsens",
      "home_team_id": 404,
      "home_team_logo": "https://media.api-sports.io/football/teams/404.png",
      "away_team": "Kolding IF",
      "away_team_id": 4676,
      "away_team_logo": "https://media.api-sports.io/football/teams/4676.png",
      "favorite_side": "home",
      "favorite": "AC Horsens",
      "underdog": "Kolding IF",
      "odds": {
        "home_win": 1.463076923076923,
        "draw": 4.046153846153846,
        "away_win": 6.246153846153846,
        "score_1x0": 5.882727272727272,
        "score_0x1": 13.721,
        "over25": 1.8445454545454547,
        "btts_yes": 1.924,
        "prob_1x0": 17.0,
        "prob_0x1": 7.3,
        "short_score_risk": 24.3,
        "favorite_odd": 1.463076923076923,
        "best_goleada_odd": 9.42909090909091
      },
      "home_stats": {
        "rank": 6,
        "goals_avg": 1.6,
        "goals_conceded_avg": 0.3,
        "over25_pct": 20.0,
        "btts_pct": 30.0,
        "draw_pct": 30.0,
        "form": "WWDWW",
        "offensive_strength": 1.23,
        "defensive_fragility": 0.23,
        "avg_shots_on_goal": 0.0,
        "avg_possession": 0.0,
        "avg_corners": 0.0,
        "pressure_index": 0.0,
        "win_pct": 70.0
      },
      "away_stats": {
        "rank": 5,
        "goals_avg": 0.8,
        "goals_conceded_avg": 1.7,
        "over25_pct": 50.0,
        "btts_pct": 50.0,
        "draw_pct": 20.0,
        "form": "LWLLD",
        "offensive_strength": 0.62,
        "defensive_fragility": 1.31,
        "avg_shots_on_goal": 0.0,
        "avg_possession": 0.0,
        "avg_corners": 0.0,
        "pressure_index": 0.0,
        "win_pct": 10.0
      },
      "score": 80.8,
      "score_class": "FORTE",
      "market": "LAY ZEBRA",
      "justification": "Análise: AC Horsens em boa fase (13/15 pts); Kolding IF raramente vence (10% vitórias). Probabilidade de Zebra é baixa.",
      "risk_note": "Lembre-se: Ganhamos no Empate ou Vitória do Favorito. Perigo apenas se a Zebra vencer.",
      "passed_filters": true,
      "filter_rejections": [],
      "stage": "operation",
      "status": "green",
      "final_score": "1x0",
      "pnl": 149.22,
      "resistance_index": 0.0,
      "fair_odd": 13.85,
      "prob_lose_pct": 7.22,
      "fair_note": "xG 2.27/0.45 | calibrado c/ O2.5 | P(avg 1x0/0x1) | mercado score_0x1 → 6.3% | blend 55/45",
      "manual_odd": 7.4,
      "lay_stake": 156.25,
      "lay_profit_green": 149.22,
      "lay_loss_red": -1000.0,
      "ev_pct": 46.57
    },
    {
      "fixture_id": 1546800,
      "strategy": "back_btts",
      "league": "Primera División - Apertura",
      "league_id": 268,
      "league_country": "Uruguay",
      "league_logo": "https://media.api-sports.io/football/leagues/268.png",
      "date": "2026-05-31",
      "time": "10:00",
      "venue": "Estadio Luis Franzini",
      "home_team": "Albion FC",
      "home_team_id": 2378,
      "home_team_logo": "https://media.api-sports.io/football/teams/2378.png",
      "away_team": "Atletico Torque",
      "away_team_id": 2365,
      "away_team_logo": "https://media.api-sports.io/football/teams/2365.png",
      "favorite_side": "away",
      "favorite": "Atletico Torque",
      "underdog": "Albion FC",
      "odds": {
        "home_win": 2.8969230769230774,
        "draw": 3.133846153846154,
        "away_win": 2.3400000000000003,
        "score_1x0": 7.619090909090909,
        "score_0x1": 6.651000000000001,
        "over25": 2.1236363636363635,
        "btts_yes": 1.825,
        "prob_1x0": 13.1,
        "prob_0x1": 15.0,
        "short_score_risk": 28.2,
        "favorite_odd": 2.3400000000000003,
        "best_goleada_odd": 18.525
      },
      "home_stats": {
        "rank": null,
        "goals_avg": 1.8,
        "goals_conceded_avg": 1.0,
        "over25_pct": 60.0,
        "over15_pct": 60.0,
        "goals_scored_home_avg": 2.4,
        "goals_scored_away_avg": 1.2,
        "goals_conceded_home_avg": 1.4,
        "goals_conceded_away_avg": 0.6,
        "scored_in_home_pct": 80.0,
        "scored_in_away_pct": 80.0,
        "conceded_in_home_pct": 80.0,
        "conceded_in_away_pct": 60.0,
        "over15_home_pct": 80.0,
        "over15_away_pct": 40.0,
        "btts_pct": 60.0,
        "draw_pct": 20.0,
        "form": "WLLDW",
        "offensive_strength": 1.38,
        "defensive_fragility": 0.77,
        "avg_shots_on_goal": 0.0,
        "avg_possession": 0.0,
        "avg_corners": 0.0,
        "pressure_index": 0.0,
        "win_pct": 60.0
      },
      "away_stats": {
        "rank": 7,
        "goals_avg": 1.8,
        "goals_conceded_avg": 1.5,
        "over25_pct": 80.0,
        "over15_pct": 90.0,
        "goals_scored_home_avg": 2.0,
        "goals_scored_away_avg": 1.6,
        "goals_conceded_home_avg": 1.6,
        "goals_conceded_away_avg": 1.4,
        "scored_in_home_pct": 100.0,
        "scored_in_away_pct": 100.0,
        "conceded_in_home_pct": 80.0,
        "conceded_in_away_pct": 100.0,
        "over15_home_pct": 80.0,
        "over15_away_pct": 100.0,
        "btts_pct": 90.0,
        "draw_pct": 20.0,
        "form": "LWDWW",
        "offensive_strength": 1.38,
        "defensive_fragility": 1.15,
        "avg_shots_on_goal": 5.0,
        "avg_possession": 40.5,
        "avg_corners": 6.5,
        "pressure_index": 57.0,
        "win_pct": 50.0
      },
      "score": 80.7,
      "score_class": "FORTE",
      "market": "BACK BTTS",
      "justification": "BTTS médio 75%; Albion FC marca em casa 80%, Atletico Torque marca fora 100%; odd BTTS 1.82",
      "risk_note": "Perde se qualquer time zerar. Casa sofre em casa 80%, Fora sofre fora 100%.",
      "passed_filters": true,
      "filter_rejections": [],
      "stage": "rejected_by_odd",
      "status": "pending",
      "final_score": "",
      "pnl": 0.0,
      "resistance_index": 0.0,
      "recommended_odd": 0.0,
      "league_avg_goals": 0.0,
      "league_edge_pct": 0.0,
      "fair_odd": 1.98,
      "prob_lose_pct": 50.59,
      "fair_note": "xG 1.49/0.96 | calibrado c/ O2.5 | Poisson+DC P(BTTS) | mercado BTTS Sim → 51.7% | P(BTTS Sim) | blend 55/45",
      "manual_odd": 50.0,
      "reject_reason": "Odd Lay muito alta para back_btts (50.0 > 25.0)",
      "ev_pct": 2429.5
    },
    {
      "fixture_id": 1545035,
      "strategy": "lay_empate",
      "league": "Friendlies",
      "league_id": 10,
      "league_country": "World",
      "league_logo": "https://media.api-sports.io/football/leagues/10.png",
      "date": "2026-05-31",
      "time": "11:00",
      "venue": "epet ARENA",
      "home_team": "Czech Republic",
      "home_team_id": 770,
      "home_team_logo": "https://media.api-sports.io/football/teams/770.png",
      "away_team": "Kosovo",
      "away_team_id": 1111,
      "away_team_logo": "https://media.api-sports.io/football/teams/1111.png",
      "favorite_side": "home",
      "favorite": "Czech Republic",
      "underdog": "Kosovo",
      "odds": {
        "home_win": 1.6791666666666665,
        "draw": 3.5924999999999994,
        "away_win": 4.954166666666666,
        "score_1x0": 5.92,
        "score_0x1": 11.431000000000001,
        "over25": 2.005,
        "btts_yes": 1.9188888888888889,
        "prob_1x0": 16.9,
        "prob_0x1": 8.7,
        "short_score_risk": 25.6,
        "favorite_odd": 1.6791666666666665,
        "best_goleada_odd": 11.975
      },
      "home_stats": {
        "rank": null,
        "goals_avg": 2.0,
        "goals_conceded_avg": 0.9,
        "over25_pct": 50.0,
        "btts_pct": 40.0,
        "draw_pct": 20.0,
        "form": "WWWLD",
        "offensive_strength": 1.54,
        "defensive_fragility": 0.69,
        "avg_shots_on_goal": 3.5,
        "avg_possession": 63.0,
        "avg_corners": 7.5,
        "pressure_index": 94.0,
        "win_pct": 60.0
      },
      "away_stats": {
        "rank": null,
        "goals_avg": 1.5,
        "goals_conceded_avg": 1.3,
        "over25_pct": 40.0,
        "btts_pct": 40.0,
        "draw_pct": 20.0,
        "form": "LLWDW",
        "offensive_strength": 1.15,
        "defensive_fragility": 1.0,
        "avg_shots_on_goal": 4.5,
        "avg_possession": 45.5,
        "avg_corners": 4.0,
        "pressure_index": 53.0,
        "win_pct": 50.0
      },
      "score": 80.9,
      "score_class": "FORTE",
      "market": "LAY EMPATE",
      "justification": "Jogo ofensivo (média combinada 3.5 gols/j); favorito claro (odd 1.68)",
      "risk_note": "Risco se jogo travar em 0x0/1x1 — odd empate 3.59",
      "passed_filters": true,
      "filter_rejections": [],
      "stage": "operation",
      "status": "green",
      "final_score": "2x1",
      "pnl": 280.88,
      "resistance_index": 0.0,
      "fair_odd": 3.72,
      "prob_lose_pct": 26.91,
      "fair_note": "xG 1.67/0.89 | calibrado c/ O2.5 | Poisson+DC P(empate) | mercado devig 1x2 → 25.9% | blend 55/45",
      "manual_odd": 4.4,
      "lay_stake": 294.12,
      "lay_profit_green": 280.88,
      "lay_loss_red": -1000.0,
      "ev_pct": -18.4
    },
    {
      "fixture_id": 1492282,
      "strategy": "back_btts",
      "league": "Serie A",
      "league_id": 71,
      "league_country": "Brazil",
      "league_logo": "https://media.api-sports.io/football/leagues/71.png",
      "date": "2026-05-31",
      "time": "11:00",
      "venue": "Estádio Cícero de Souza Marques",
      "home_team": "RB Bragantino",
      "home_team_id": 794,
      "home_team_logo": "https://media.api-sports.io/football/teams/794.png",
      "away_team": "Internacional",
      "away_team_id": 119,
      "away_team_logo": "https://media.api-sports.io/football/teams/119.png",
      "favorite_side": "home",
      "favorite": "RB Bragantino",
      "underdog": "Internacional",
      "odds": {
        "home_win": 2.1346153846153846,
        "draw": 3.3392307692307694,
        "away_win": 3.375384615384615,
        "score_1x0": 7.078181818181818,
        "score_0x1": 9.287,
        "over25": 1.9590909090909088,
        "btts_yes": 1.735,
        "prob_1x0": 14.1,
        "prob_0x1": 10.8,
        "short_score_risk": 24.9,
        "favorite_odd": 2.1346153846153846,
        "best_goleada_odd": 16.186363636363637
      },
      "home_stats": {
        "rank": 10,
        "goals_avg": 2.0,
        "goals_conceded_avg": 0.8,
        "over25_pct": 50.0,
        "over15_pct": 90.0,
        "goals_scored_home_avg": 1.75,
        "goals_scored_away_avg": 2.1666666666666665,
        "goals_conceded_home_avg": 0.5,
        "goals_conceded_away_avg": 1.0,
        "scored_in_home_pct": 75.0,
        "scored_in_away_pct": 83.33333333333334,
        "conceded_in_home_pct": 50.0,
        "conceded_in_away_pct": 66.66666666666666,
        "over15_home_pct": 75.0,
        "over15_away_pct": 100.0,
        "btts_pct": 40.0,
        "draw_pct": 10.0,
        "form": "WWWDW",
        "offensive_strength": 1.54,
        "defensive_fragility": 0.62,
        "avg_shots_on_goal": 6.2,
        "avg_possession": 49.2,
        "avg_corners": 5.6,
        "pressure_index": 80.4,
        "win_pct": 60.0
      },
      "away_stats": {
        "rank": 16,
        "goals_avg": 1.7,
        "goals_conceded_avg": 1.5,
        "over25_pct": 70.0,
        "over15_pct": 90.0,
        "goals_scored_home_avg": 2.0,
        "goals_scored_away_avg": 1.4,
        "goals_conceded_home_avg": 1.0,
        "goals_conceded_away_avg": 2.0,
        "scored_in_home_pct": 80.0,
        "scored_in_away_pct": 80.0,
        "conceded_in_home_pct": 60.0,
        "conceded_in_away_pct": 100.0,
        "over15_home_pct": 80.0,
        "over15_away_pct": 100.0,
        "btts_pct": 70.0,
        "draw_pct": 30.0,
        "form": "LLWWD",
        "offensive_strength": 1.31,
        "defensive_fragility": 1.15,
        "avg_shots_on_goal": 4.2,
        "avg_possession": 53.4,
        "avg_corners": 4.2,
        "pressure_index": 67.2,
        "win_pct": 40.0
      },
      "score": 72.8,
      "score_class": "BOA",
      "market": "BACK BTTS",
      "justification": "BTTS médio 55%; RB Bragantino marca em casa 75%, Internacional marca fora 80%; odd BTTS 1.74",
      "risk_note": "Perde se qualquer time zerar. Casa sofre em casa 50%, Fora sofre fora 100%.",
      "passed_filters": true,
      "filter_rejections": [],
      "stage": "operation",
      "status": "green",
      "final_score": "3x1",
      "pnl": 983.65,
      "resistance_index": 0.0,
      "recommended_odd": 0.0,
      "league_avg_goals": 0.0,
      "league_edge_pct": 0.0,
      "fair_odd": 1.93,
      "prob_lose_pct": 51.75,
      "fair_note": "xG 1.73/0.87 | calibrado c/ O2.5 | Poisson+DC P(BTTS) | mercado BTTS Sim → 54.4% | P(BTTS Sim) | blend 55/45",
      "manual_odd": 2.03,
      "lay_stake": 1000.0,
      "lay_profit_green": 983.65,
      "lay_loss_red": -1000.0,
      "ev_pct": 5.05
    },
    {
      "fixture_id": 1545035,
      "strategy": "back_favorito",
      "league": "Friendlies",
      "league_id": 10,
      "league_country": "World",
      "league_logo": "https://media.api-sports.io/football/leagues/10.png",
      "date": "2026-05-31",
      "time": "11:00",
      "venue": "epet ARENA",
      "home_team": "Czech Republic",
      "home_team_id": 770,
      "home_team_logo": "https://media.api-sports.io/football/teams/770.png",
      "away_team": "Kosovo",
      "away_team_id": 1111,
      "away_team_logo": "https://media.api-sports.io/football/teams/1111.png",
      "favorite_side": "home",
      "favorite": "Czech Republic",
      "underdog": "Kosovo",
      "odds": {
        "home_win": 1.6791666666666665,
        "draw": 3.5924999999999994,
        "away_win": 4.954166666666666,
        "score_1x0": 5.92,
        "score_0x1": 11.431000000000001,
        "over25": 2.005,
        "btts_yes": 1.9188888888888889,
        "prob_1x0": 16.9,
        "prob_0x1": 8.7,
        "short_score_risk": 25.6,
        "favorite_odd": 1.6791666666666665,
        "best_goleada_odd": 11.975
      },
      "home_stats": {
        "rank": null,
        "goals_avg": 2.0,
        "goals_conceded_avg": 0.9,
        "over25_pct": 50.0,
        "btts_pct": 40.0,
        "draw_pct": 20.0,
        "form": "WWWLD",
        "offensive_strength": 1.54,
        "defensive_fragility": 0.69,
        "avg_shots_on_goal": 3.5,
        "avg_possession": 63.0,
        "avg_corners": 7.5,
        "pressure_index": 94.0,
        "win_pct": 60.0
      },
      "away_stats": {
        "rank": null,
        "goals_avg": 1.5,
        "goals_conceded_avg": 1.3,
        "over25_pct": 40.0,
        "btts_pct": 40.0,
        "draw_pct": 20.0,
        "form": "LLWDW",
        "offensive_strength": 1.15,
        "defensive_fragility": 1.0,
        "avg_shots_on_goal": 4.5,
        "avg_possession": 45.5,
        "avg_corners": 4.0,
        "pressure_index": 53.0,
        "win_pct": 50.0
      },
      "score": 66.7,
      "score_class": "BOA",
      "market": "BACK FAVORITO",
      "justification": "Czech Republic WR 60%, forma WWWLD vs Kosovo WR 50% — odd 1.68",
      "risk_note": "Perde se empate (odd 3.59) ou vitória da zebra. Comissão 4.5% aplicada no green.",
      "passed_filters": true,
      "filter_rejections": [],
      "stage": "operation",
      "status": "green",
      "final_score": "2x1",
      "pnl": 916.8,
      "resistance_index": 0.0,
      "fair_odd": 1.83,
      "prob_lose_pct": 54.6,
      "fair_note": "xG 1.67/0.89 | calibrado c/ O2.5 | mercado 1x2 fav → 55.4% | P(Fav Win) | blend 55/45",
      "manual_odd": 1.96,
      "lay_stake": 1000.0,
      "lay_profit_green": 916.8,
      "lay_loss_red": -1000.0,
      "ev_pct": -7.02
    },
    {
      "fixture_id": 1495849,
      "strategy": "lay_zebrao",
      "league": "1. Division",
      "league_id": 104,
      "league_country": "Norway",
      "league_logo": "https://media.api-sports.io/football/leagues/104.png",
      "date": "2026-05-31",
      "time": "12:00",
      "venue": "Gjemselund Stadion",
      "home_team": "Kongsvinger",
      "home_team_id": 2144,
      "home_team_logo": "https://media.api-sports.io/football/teams/2144.png",
      "away_team": "Asane",
      "away_team_id": 2148,
      "away_team_logo": "https://media.api-sports.io/football/teams/2148.png",
      "favorite_side": "home",
      "favorite": "Kongsvinger",
      "underdog": "Asane",
      "odds": {
        "home_win": 1.3015384615384618,
        "draw": 5.432307692307693,
        "away_win": 7.353076923076923,
        "score_1x0": 10.799090909090909,
        "score_0x1": 27.568,
        "over25": 1.306,
        "btts_yes": 1.534,
        "prob_1x0": 9.3,
        "prob_0x1": 3.6,
        "short_score_risk": 12.9,
        "favorite_odd": 1.3015384615384618,
        "best_goleada_odd": 8.923636363636364
      },
      "home_stats": {
        "rank": 3,
        "goals_avg": 2.3,
        "goals_conceded_avg": 1.1,
        "over25_pct": 80.0,
        "btts_pct": 70.0,
        "draw_pct": 20.0,
        "form": "WLWWD",
        "offensive_strength": 1.77,
        "defensive_fragility": 0.85,
        "avg_shots_on_goal": 0.0,
        "avg_possession": 0.0,
        "avg_corners": 0.0,
        "pressure_index": 0.0,
        "win_pct": 70.0
      },
      "away_stats": {
        "rank": 12,
        "goals_avg": 1.3,
        "goals_conceded_avg": 2.2,
        "over25_pct": 60.0,
        "btts_pct": 40.0,
        "draw_pct": 10.0,
        "form": "LWWDL",
        "offensive_strength": 1.0,
        "defensive_fragility": 1.69,
        "avg_shots_on_goal": 0.0,
        "avg_possession": 0.0,
        "avg_corners": 0.0,
        "pressure_index": 0.0,
        "win_pct": 20.0
      },
      "score": 80.5,
      "score_class": "FORTE",
      "market": "LAY ZEBRÃO",
      "justification": "Kongsvinger ataque 2.3, Over2.5 80% — zebra (Asane) odd 7.35, sofre 2.2/j",
      "risk_note": "Operação in-play: sair em 0-0 HT, gol da zebra ou red. Seguir se favorito marcar primeiro. PnL informado manualmente.",
      "passed_filters": true,
      "filter_rejections": [],
      "stage": "operation",
      "status": "red",
      "final_score": "manual",
      "pnl": -141.0,
      "resistance_index": 0.0,
      "lay_stake": 1000.0,
      "fair_odd": 30.05,
      "prob_lose_pct": 3.33,
      "fair_note": "xG 2.78/0.97 | calibrado c/ O2.5 | P(avg 1x0/0x1) | mercado score_0x1 → 3.2% | blend 55/45",
      "manual_pnl": -141.0
    },
    {
      "fixture_id": 1495849,
      "strategy": "lay_zebra",
      "league": "1. Division",
      "league_id": 104,
      "league_country": "Norway",
      "league_logo": "https://media.api-sports.io/football/leagues/104.png",
      "date": "2026-05-31",
      "time": "12:00",
      "venue": "Gjemselund Stadion",
      "home_team": "Kongsvinger",
      "home_team_id": 2144,
      "home_team_logo": "https://media.api-sports.io/football/teams/2144.png",
      "away_team": "Asane",
      "away_team_id": 2148,
      "away_team_logo": "https://media.api-sports.io/football/teams/2148.png",
      "favorite_side": "home",
      "favorite": "Kongsvinger",
      "underdog": "Asane",
      "odds": {
        "home_win": 1.3015384615384618,
        "draw": 5.432307692307693,
        "away_win": 7.353076923076923,
        "score_1x0": 10.799090909090909,
        "score_0x1": 27.568,
        "over25": 1.306,
        "btts_yes": 1.534,
        "prob_1x0": 9.3,
        "prob_0x1": 3.6,
        "short_score_risk": 12.9,
        "favorite_odd": 1.3015384615384618,
        "best_goleada_odd": 8.923636363636364
      },
      "home_stats": {
        "rank": 3,
        "goals_avg": 2.3,
        "goals_conceded_avg": 1.1,
        "over25_pct": 80.0,
        "btts_pct": 70.0,
        "draw_pct": 20.0,
        "form": "WLWWD",
        "offensive_strength": 1.77,
        "defensive_fragility": 0.85,
        "avg_shots_on_goal": 0.0,
        "avg_possession": 0.0,
        "avg_corners": 0.0,
        "pressure_index": 0.0,
        "win_pct": 70.0
      },
      "away_stats": {
        "rank": 12,
        "goals_avg": 1.3,
        "goals_conceded_avg": 2.2,
        "over25_pct": 60.0,
        "btts_pct": 40.0,
        "draw_pct": 10.0,
        "form": "LWWDL",
        "offensive_strength": 1.0,
        "defensive_fragility": 1.69,
        "avg_shots_on_goal": 0.0,
        "avg_possession": 0.0,
        "avg_corners": 0.0,
        "pressure_index": 0.0,
        "win_pct": 20.0
      },
      "score": 80.5,
      "score_class": "FORTE",
      "market": "LAY ZEBRA",
      "justification": "Análise: Kongsvinger em boa fase (10/15 pts); Asane raramente vence (20% vitórias). Probabilidade de Zebra é baixa.",
      "risk_note": "Lembre-se: Ganhamos no Empate ou Vitória do Favorito. Perigo apenas se a Zebra vencer.",
      "passed_filters": true,
      "filter_rejections": [],
      "stage": "operation",
      "status": "green",
      "final_score": "3x1",
      "pnl": 113.69,
      "resistance_index": 0.0,
      "fair_odd": 30.05,
      "prob_lose_pct": 3.33,
      "fair_note": "xG 2.78/0.97 | calibrado c/ O2.5 | P(avg 1x0/0x1) | mercado score_0x1 → 3.2% | blend 55/45",
      "manual_odd": 9.4,
      "lay_stake": 119.05,
      "lay_profit_green": 113.69,
      "lay_loss_red": -1000.0,
      "ev_pct": 68.7
    },
    {
      "fixture_id": 1495847,
      "strategy": "lay_empate",
      "league": "1. Division",
      "league_id": 104,
      "league_country": "Norway",
      "league_logo": "https://media.api-sports.io/football/leagues/104.png",
      "date": "2026-05-31",
      "time": "12:00",
      "venue": "Bryne Stadion",
      "home_team": "Bryne",
      "home_team_id": 2142,
      "home_team_logo": "https://media.api-sports.io/football/teams/2142.png",
      "away_team": "hodd",
      "away_team_id": 2150,
      "away_team_logo": "https://media.api-sports.io/football/teams/2150.png",
      "favorite_side": "home",
      "favorite": "Bryne",
      "underdog": "hodd",
      "odds": {
        "home_win": 1.6576923076923078,
        "draw": 3.7530769230769225,
        "away_win": 4.626153846153846,
        "score_1x0": 7.633636363636364,
        "score_0x1": 13.846,
        "over25": 1.6445454545454545,
        "btts_yes": 1.621,
        "prob_1x0": 13.1,
        "prob_0x1": 7.2,
        "short_score_risk": 20.3,
        "favorite_odd": 1.6576923076923078,
        "best_goleada_odd": 11.141818181818183
      },
      "home_stats": {
        "rank": null,
        "goals_avg": 1.4,
        "goals_conceded_avg": 2.0,
        "over25_pct": 70.0,
        "btts_pct": 50.0,
        "draw_pct": 10.0,
        "form": "WLLWW",
        "offensive_strength": 1.08,
        "defensive_fragility": 1.54,
        "avg_shots_on_goal": 0.0,
        "avg_possession": 0.0,
        "avg_corners": 0.0,
        "pressure_index": 0.0,
        "win_pct": 30.0
      },
      "away_stats": {
        "rank": 10,
        "goals_avg": 1.3,
        "goals_conceded_avg": 1.3,
        "over25_pct": 50.0,
        "btts_pct": 60.0,
        "draw_pct": 20.0,
        "form": "LWLDW",
        "offensive_strength": 1.0,
        "defensive_fragility": 1.0,
        "avg_shots_on_goal": 0.0,
        "avg_possession": 0.0,
        "avg_corners": 0.0,
        "pressure_index": 0.0,
        "win_pct": 40.0
      },
      "score": 70.9,
      "score_class": "BOA",
      "market": "LAY EMPATE",
      "justification": "Jogo ofensivo (média combinada 2.7 gols/j); favorito claro (odd 1.66)",
      "risk_note": "Risco se jogo travar em 0x0/1x1 — odd empate 3.75",
      "passed_filters": true,
      "filter_rejections": [],
      "stage": "operation",
      "status": "green",
      "final_score": "1x0",
      "pnl": 289.39,
      "resistance_index": 0.0,
      "fair_odd": 3.8,
      "prob_lose_pct": 26.29,
      "fair_note": "xG 1.45/1.53 | calibrado c/ O2.5 | Poisson+DC P(empate) | mercado devig 1x2 → 24.5% | blend 55/45",
      "manual_odd": 4.3,
      "lay_stake": 303.03,
      "lay_profit_green": 289.39,
      "lay_loss_red": -1000.0,
      "ev_pct": -13.05
    },
    {
      "fixture_id": 1495852,
      "strategy": "lay_0x1",
      "league": "1. Division",
      "league_id": 104,
      "league_country": "Norway",
      "league_logo": "https://media.api-sports.io/football/leagues/104.png",
      "date": "2026-05-31",
      "time": "12:00",
      "venue": "EXTRA Arena",
      "home_team": "Ranheim",
      "home_team_id": 322,
      "home_team_logo": "https://media.api-sports.io/football/teams/322.png",
      "away_team": "Sandnes ULF",
      "away_team_id": 2146,
      "away_team_logo": "https://media.api-sports.io/football/teams/2146.png",
      "favorite_side": "home",
      "favorite": "Ranheim",
      "underdog": "Sandnes ULF",
      "odds": {
        "home_win": 1.8169230769230773,
        "draw": 3.891538461538462,
        "away_win": 3.5523076923076924,
        "score_1x0": 10.372727272727273,
        "score_0x1": 14.465,
        "over25": 1.4309999999999996,
        "btts_yes": 1.4269999999999998,
        "prob_1x0": 9.6,
        "prob_0x1": 6.9,
        "short_score_risk": 16.6,
        "favorite_odd": 1.8169230769230773,
        "best_goleada_odd": 11.32181818181818
      },
      "home_stats": {
        "rank": 6,
        "goals_avg": 2.6,
        "goals_conceded_avg": 1.8,
        "over25_pct": 80.0,
        "btts_pct": 70.0,
        "draw_pct": 20.0,
        "form": "WLWLD",
        "offensive_strength": 2.0,
        "defensive_fragility": 1.38,
        "avg_shots_on_goal": 0.0,
        "avg_possession": 0.0,
        "avg_corners": 0.0,
        "pressure_index": 0.0,
        "win_pct": 50.0
      },
      "away_stats": {
        "rank": null,
        "goals_avg": 1.2,
        "goals_conceded_avg": 1.8,
        "over25_pct": 40.0,
        "btts_pct": 50.0,
        "draw_pct": 10.0,
        "form": "LWLWL",
        "offensive_strength": 0.92,
        "defensive_fragility": 1.38,
        "avg_shots_on_goal": 0.0,
        "avg_possession": 0.0,
        "avg_corners": 0.0,
        "pressure_index": 0.0,
        "win_pct": 30.0
      },
      "score": 62.0,
      "score_class": "REGULAR",
      "market": "LAY 1x0",
      "justification": "Ranheim artilheiro (2.6 gols/jogo); Sandnes ULF frágil (1.8 sofridos/jogo); alta tendência Over 2.5 (80%)",
      "risk_note": "risco combinado moderado (16.6%)",
      "passed_filters": true,
      "filter_rejections": [],
      "stage": "operation",
      "status": "green",
      "final_score": "5x1",
      "pnl": 63.67,
      "resistance_index": 0.0,
      "fair_odd": 19.47,
      "prob_lose_pct": 5.14,
      "fair_note": "xG 2.29/1.10 | calibrado c/ O2.5 | P(avg 1x0/0x1) | mercado score_0x1 → 6.0% | blend 55/45",
      "manual_odd": 16.0,
      "lay_stake": 66.67,
      "lay_profit_green": 63.67,
      "lay_loss_red": -1000.0,
      "ev_pct": 17.76
    },
    {
      "fixture_id": 1504236,
      "strategy": "lay_0x1_zebra",
      "league": "Ykkösliiga",
      "league_id": 1087,
      "league_country": "Finland",
      "league_logo": "https://media.api-sports.io/football/leagues/1087.png",
      "date": "2026-05-31",
      "time": "12:00",
      "venue": "Markku.fi Areena",
      "home_team": "PK-35",
      "home_team_id": 10669,
      "home_team_logo": "https://media.api-sports.io/football/teams/10669.png",
      "away_team": "Klubi-04",
      "away_team_id": 2085,
      "away_team_logo": "https://media.api-sports.io/football/teams/2085.png",
      "favorite_side": "home",
      "favorite": "PK-35",
      "underdog": "Klubi-04",
      "odds": {
        "home_win": 1.7541666666666667,
        "draw": 3.5575000000000006,
        "away_win": 4.001666666666667,
        "score_1x0": 7.071111111111112,
        "score_0x1": 11.395555555555555,
        "over25": 1.7049999999999996,
        "btts_yes": 1.6300000000000001,
        "prob_1x0": 14.1,
        "prob_0x1": 8.8,
        "short_score_risk": 22.9,
        "favorite_odd": 1.7541666666666667,
        "best_goleada_odd": 11.38888888888889
      },
      "home_stats": {
        "rank": 5,
        "goals_avg": 1.5,
        "goals_conceded_avg": 0.7,
        "over25_pct": 20.0,
        "btts_pct": 30.0,
        "draw_pct": 20.0,
        "form": "DWWDL",
        "offensive_strength": 1.15,
        "defensive_fragility": 0.54,
        "avg_shots_on_goal": 0.0,
        "avg_possession": 0.0,
        "avg_corners": 0.0,
        "pressure_index": 0.0,
        "win_pct": 50.0
      },
      "away_stats": {
        "rank": 6,
        "goals_avg": 0.6,
        "goals_conceded_avg": 1.2,
        "over25_pct": 20.0,
        "btts_pct": 60.0,
        "draw_pct": 40.0,
        "form": "DLLDD",
        "offensive_strength": 0.46,
        "defensive_fragility": 0.92,
        "avg_shots_on_goal": 0.0,
        "avg_possession": 0.0,
        "avg_corners": 0.0,
        "pressure_index": 0.0,
        "win_pct": 0.0
      },
      "score": 59.8,
      "score_class": "REGULAR",
      "market": "LAY 0x1",
      "justification": "PK-35 ataque 1.5, sofridos 0.7 — Klubi-04 ataque fraco 0.6",
      "risk_note": "Lembre-se: Ganhamos se o favorito marcar ou se o jogo empatar/zebra não fizer 0x1. Odd limite do Lay: 20.0.",
      "passed_filters": true,
      "filter_rejections": [],
      "stage": "rejected_by_odd",
      "pnl": 0,
      "resistance_index": 0.0,
      "fair_odd": 14.05,
      "prob_lose_pct": 7.12,
      "fair_note": "xG 2.18/0.72 | calibrado c/ O2.5 | P(avg 1x0/0x1) | mercado score_0x1 → 7.6% | blend 55/45",
      "manual_odd": 50.0,
      "reject_reason": "Odd Lay muito alta para lay_0x1_zebra (50.0 > 20.0)",
      "ev_pct": -256.0
    },
    {
      "fixture_id": 1495853,
      "strategy": "lay_0x1",
      "league": "1. Division",
      "league_id": 104,
      "league_country": "Norway",
      "league_logo": "https://media.api-sports.io/football/leagues/104.png",
      "date": "2026-05-31",
      "time": "12:00",
      "venue": "NAMMO Stadion",
      "home_team": "Raufoss",
      "home_team_id": 2153,
      "home_team_logo": "https://media.api-sports.io/football/teams/2153.png",
      "away_team": "Haugesund",
      "away_team_id": 328,
      "away_team_logo": "https://media.api-sports.io/football/teams/328.png",
      "favorite_side": "away",
      "favorite": "Haugesund",
      "underdog": "Raufoss",
      "odds": {
        "home_win": 3.6615384615384623,
        "draw": 3.813846153846154,
        "away_win": 1.806923076923077,
        "score_1x0": 13.88090909090909,
        "score_0x1": 9.306000000000001,
        "over25": 1.496,
        "btts_yes": 1.48,
        "prob_1x0": 7.2,
        "prob_0x1": 10.7,
        "short_score_risk": 17.9,
        "favorite_odd": 1.806923076923077,
        "best_goleada_odd": 11.181000000000001
      },
      "home_stats": {
        "rank": 13,
        "goals_avg": 1.2,
        "goals_conceded_avg": 2.1,
        "over25_pct": 70.0,
        "btts_pct": 60.0,
        "draw_pct": 10.0,
        "form": "LLWWL",
        "offensive_strength": 0.92,
        "defensive_fragility": 1.62,
        "avg_shots_on_goal": 0.0,
        "avg_possession": 0.0,
        "avg_corners": 0.0,
        "pressure_index": 0.0,
        "win_pct": 20.0
      },
      "away_stats": {
        "rank": null,
        "goals_avg": 3.0,
        "goals_conceded_avg": 1.7,
        "over25_pct": 70.0,
        "btts_pct": 70.0,
        "draw_pct": 10.0,
        "form": "WWWDL",
        "offensive_strength": 2.31,
        "defensive_fragility": 1.31,
        "avg_shots_on_goal": 0.0,
        "avg_possession": 0.0,
        "avg_corners": 0.0,
        "pressure_index": 0.0,
        "win_pct": 70.0
      },
      "score": 52.9,
      "score_class": "REGULAR",
      "market": "LAY 0x1",
      "justification": "Haugesund artilheiro (3.0 gols/jogo); Raufoss frágil (2.1 sofridos/jogo); alta tendência Over 2.5 (70%); boa forma (WWWDL)",
      "risk_note": "risco combinado moderado (17.9%)",
      "passed_filters": true,
      "filter_rejections": [],
      "stage": "operation",
      "status": "green",
      "final_score": "3x4",
      "pnl": 68.21,
      "resistance_index": 0.0,
      "fair_odd": 14.51,
      "prob_lose_pct": 6.89,
      "fair_note": "xG 1.16/2.09 | calibrado c/ O2.5 | P(avg 1x0/0x1) | mercado score_0x1 → 9.3% | blend 55/45",
      "manual_odd": 15.0,
      "lay_stake": 71.43,
      "lay_profit_green": 68.21,
      "lay_loss_red": -1000.0,
      "ev_pct": -3.35
    },
    {
      "fixture_id": 1544805,
      "strategy": "back_btts",
      "league": "Friendlies",
      "league_id": 10,
      "league_country": "World",
      "league_logo": "https://media.api-sports.io/football/leagues/10.png",
      "date": "2026-05-31",
      "time": "12:30",
      "venue": "Tarczyński Arena Wrocław",
      "home_team": "Poland",
      "home_team_id": 24,
      "home_team_logo": "https://media.api-sports.io/football/teams/24.png",
      "away_team": "Ukraine",
      "away_team_id": 772,
      "away_team_logo": "https://media.api-sports.io/football/teams/772.png",
      "favorite_side": "home",
      "favorite": "Poland",
      "underdog": "Ukraine",
      "odds": {
        "home_win": 2.055833333333333,
        "draw": 3.294166666666667,
        "away_win": 3.4875000000000007,
        "score_1x0": 6.553,
        "score_0x1": 9.092,
        "over25": 2.0380000000000003,
        "btts_yes": 1.8033333333333337,
        "prob_1x0": 15.3,
        "prob_0x1": 11.0,
        "short_score_risk": 26.3,
        "favorite_odd": 2.055833333333333,
        "best_goleada_odd": 15.705000000000002
      },
      "home_stats": {
        "rank": null,
        "goals_avg": 1.7,
        "goals_conceded_avg": 1.3,
        "over25_pct": 50.0,
        "over15_pct": 90.0,
        "goals_scored_home_avg": 1.5,
        "goals_scored_away_avg": 2.0,
        "goals_conceded_home_avg": 1.1666666666666667,
        "goals_conceded_away_avg": 1.5,
        "scored_in_home_pct": 83.33333333333334,
        "scored_in_away_pct": 100.0,
        "conceded_in_home_pct": 83.33333333333334,
        "conceded_in_away_pct": 75.0,
        "over15_home_pct": 83.33333333333334,
        "over15_away_pct": 100.0,
        "btts_pct": 70.0,
        "draw_pct": 30.0,
        "form": "DLLWW",
        "offensive_strength": 1.31,
        "defensive_fragility": 1.0,
        "avg_shots_on_goal": 5.8,
        "avg_possession": 56.0,
        "avg_corners": 7.2,
        "pressure_index": 97.0,
        "win_pct": 50.0
      },
      "away_stats": {
        "rank": null,
        "goals_avg": 1.5,
        "goals_conceded_avg": 1.6,
        "over25_pct": 50.0,
        "over15_pct": 90.0,
        "goals_scored_home_avg": 1.2,
        "goals_scored_away_avg": 1.8,
        "goals_conceded_home_avg": 1.2,
        "goals_conceded_away_avg": 2.0,
        "scored_in_home_pct": 80.0,
        "scored_in_away_pct": 80.0,
        "conceded_in_home_pct": 60.0,
        "conceded_in_away_pct": 80.0,
        "over15_home_pct": 80.0,
        "over15_away_pct": 100.0,
        "btts_pct": 50.0,
        "draw_pct": 10.0,
        "form": "LWWLW",
        "offensive_strength": 1.15,
        "defensive_fragility": 1.23,
        "avg_shots_on_goal": 4.0,
        "avg_possession": 55.3,
        "avg_corners": 4.7,
        "pressure_index": 71.3,
        "win_pct": 50.0
      },
      "score": 85.7,
      "score_class": "ELITE",
      "market": "BACK BTTS",
      "justification": "BTTS médio 60%; Poland marca em casa 83%, Ukraine marca fora 80%; odd BTTS 1.80",
      "risk_note": "Perde se qualquer time zerar. Casa sofre em casa 83%, Fora sofre fora 80%.",
      "passed_filters": true,
      "filter_rejections": [],
      "stage": "operation",
      "status": "red",
      "final_score": "0x2",
      "pnl": -1000.0,
      "resistance_index": 0.0,
      "recommended_odd": 0.0,
      "league_avg_goals": 0.0,
      "league_edge_pct": 0.0,
      "fair_odd": 1.93,
      "prob_lose_pct": 51.75,
      "fair_note": "xG 1.53/1.00 | calibrado c/ O2.5 | Poisson+DC P(BTTS) | mercado BTTS Sim → 52.3% | P(BTTS Sim) | blend 55/45",
      "manual_odd": 2.03,
      "lay_stake": 1000.0,
      "lay_profit_green": 983.65,
      "lay_loss_red": -1000.0,
      "ev_pct": 5.05
    },
    {
      "fixture_id": 1544805,
      "strategy": "over_15",
      "league": "Friendlies",
      "league_id": 10,
      "league_country": "World",
      "league_logo": "https://media.api-sports.io/football/leagues/10.png",
      "date": "2026-05-31",
      "time": "12:30",
      "venue": "Tarczyński Arena Wrocław",
      "home_team": "Poland",
      "home_team_id": 24,
      "home_team_logo": "https://media.api-sports.io/football/teams/24.png",
      "away_team": "Ukraine",
      "away_team_id": 772,
      "away_team_logo": "https://media.api-sports.io/football/teams/772.png",
      "favorite_side": "home",
      "favorite": "Poland",
      "underdog": "Ukraine",
      "odds": {
        "home_win": 2.055833333333333,
        "draw": 3.294166666666667,
        "away_win": 3.4875000000000007,
        "score_1x0": 6.553,
        "score_0x1": 9.092,
        "over25": 2.0380000000000003,
        "btts_yes": 1.8033333333333337,
        "prob_1x0": 15.3,
        "prob_0x1": 11.0,
        "short_score_risk": 26.3,
        "favorite_odd": 2.055833333333333,
        "best_goleada_odd": 15.705000000000002
      },
      "home_stats": {
        "rank": null,
        "goals_avg": 1.7,
        "goals_conceded_avg": 1.3,
        "over25_pct": 50.0,
        "over15_pct": 90.0,
        "goals_scored_home_avg": 1.5,
        "goals_scored_away_avg": 2.0,
        "goals_conceded_home_avg": 1.1666666666666667,
        "goals_conceded_away_avg": 1.5,
        "scored_in_home_pct": 83.33333333333334,
        "scored_in_away_pct": 100.0,
        "conceded_in_home_pct": 83.33333333333334,
        "conceded_in_away_pct": 75.0,
        "over15_home_pct": 83.33333333333334,
        "over15_away_pct": 100.0,
        "btts_pct": 70.0,
        "draw_pct": 30.0,
        "form": "DLLWW",
        "offensive_strength": 1.31,
        "defensive_fragility": 1.0,
        "avg_shots_on_goal": 5.8,
        "avg_possession": 56.0,
        "avg_corners": 7.2,
        "pressure_index": 97.0,
        "win_pct": 50.0
      },
      "away_stats": {
        "rank": null,
        "goals_avg": 1.5,
        "goals_conceded_avg": 1.6,
        "over25_pct": 50.0,
        "over15_pct": 90.0,
        "goals_scored_home_avg": 1.2,
        "goals_scored_away_avg": 1.8,
        "goals_conceded_home_avg": 1.2,
        "goals_conceded_away_avg": 2.0,
        "scored_in_home_pct": 80.0,
        "scored_in_away_pct": 80.0,
        "conceded_in_home_pct": 60.0,
        "conceded_in_away_pct": 80.0,
        "over15_home_pct": 80.0,
        "over15_away_pct": 100.0,
        "btts_pct": 50.0,
        "draw_pct": 10.0,
        "form": "LWWLW",
        "offensive_strength": 1.15,
        "defensive_fragility": 1.23,
        "avg_shots_on_goal": 4.0,
        "avg_possession": 55.3,
        "avg_corners": 4.7,
        "pressure_index": 71.3,
        "win_pct": 50.0
      },
      "score": 77.9,
      "score_class": "FORTE",
      "market": "OVER 1.5",
      "justification": "Média Gols: 3.20; Over 1.5 geral médio: 90.0%; Casa marca em casa: 83.3%; Fora marca fora: 80.0%",
      "risk_note": "Ganhamos com 2+ gols totais na partida. BTTS geral médio: 60.0%.",
      "passed_filters": true,
      "filter_rejections": [],
      "stage": "operation",
      "status": "green",
      "final_score": "0x2",
      "pnl": 477.5,
      "resistance_index": 0.0,
      "recommended_odd": 0.0,
      "league_avg_goals": 0.0,
      "league_edge_pct": 0.0,
      "fair_odd": 1.53,
      "prob_lose_pct": 65.5,
      "fair_note": "xG 1.53/1.00 | calibrado c/ O2.5 | Poisson P(Over 1.5) | mercado Over 1.5 proxy → 55.5% | P(Over 1.5) | blend 55/45",
      "manual_odd": 1.5,
      "lay_stake": 1000.0,
      "lay_profit_green": 477.5,
      "lay_loss_red": -1000.0,
      "ev_pct": -1.75
    },
    {
      "fixture_id": 1512627,
      "strategy": "over_15",
      "league": "Primera División",
      "league_id": 281,
      "league_country": "Peru",
      "league_logo": "https://media.api-sports.io/football/leagues/281.png",
      "date": "2026-05-31",
      "time": "13:00",
      "venue": "Estadio de la UNSA",
      "home_team": "FBC Melgar",
      "home_team_id": 2554,
      "home_team_logo": "https://media.api-sports.io/football/teams/2554.png",
      "away_team": "Alianza Atletico",
      "away_team_id": 2560,
      "away_team_logo": "https://media.api-sports.io/football/teams/2560.png",
      "favorite_side": "home",
      "favorite": "FBC Melgar",
      "underdog": "Alianza Atletico",
      "odds": {
        "home_win": 1.534615384615385,
        "draw": 3.8215384615384616,
        "away_win": 5.836923076923076,
        "score_1x0": 5.565454545454545,
        "score_0x1": 12.402,
        "over25": 1.95,
        "btts_yes": 1.988,
        "prob_1x0": 18.0,
        "prob_0x1": 8.1,
        "short_score_risk": 26.0,
        "favorite_odd": 1.534615384615385,
        "best_goleada_odd": 10.166363636363636
      },
      "home_stats": {
        "rank": 7,
        "goals_avg": 1.8,
        "goals_conceded_avg": 1.1,
        "over25_pct": 50.0,
        "over15_pct": 90.0,
        "goals_scored_home_avg": 2.4,
        "goals_scored_away_avg": 1.2,
        "goals_conceded_home_avg": 1.2,
        "goals_conceded_away_avg": 1.0,
        "scored_in_home_pct": 100.0,
        "scored_in_away_pct": 80.0,
        "conceded_in_home_pct": 80.0,
        "conceded_in_away_pct": 100.0,
        "over15_home_pct": 100.0,
        "over15_away_pct": 80.0,
        "btts_pct": 80.0,
        "draw_pct": 30.0,
        "form": "WDWDW",
        "offensive_strength": 1.38,
        "defensive_fragility": 0.85,
        "avg_shots_on_goal": 6.6,
        "avg_possession": 57.6,
        "avg_corners": 5.6,
        "pressure_index": 100,
        "win_pct": 50.0
      },
      "away_stats": {
        "rank": 10,
        "goals_avg": 1.1,
        "goals_conceded_avg": 1.4,
        "over25_pct": 40.0,
        "over15_pct": 90.0,
        "goals_scored_home_avg": 1.25,
        "goals_scored_away_avg": 1.0,
        "goals_conceded_home_avg": 1.5,
        "goals_conceded_away_avg": 1.3333333333333333,
        "scored_in_home_pct": 50.0,
        "scored_in_away_pct": 66.66666666666666,
        "conceded_in_home_pct": 100.0,
        "conceded_in_away_pct": 66.66666666666666,
        "over15_home_pct": 100.0,
        "over15_away_pct": 83.33333333333334,
        "btts_pct": 50.0,
        "draw_pct": 20.0,
        "form": "LLDDW",
        "offensive_strength": 0.85,
        "defensive_fragility": 1.08,
        "avg_shots_on_goal": 4.4,
        "avg_possession": 46.4,
        "avg_corners": 2.8,
        "pressure_index": 49.2,
        "win_pct": 30.0
      },
      "score": 77.4,
      "score_class": "FORTE",
      "market": "OVER 1.5",
      "justification": "Média Gols: 2.90; Over 1.5 geral médio: 90.0%; Casa marca em casa: 100.0%; Fora marca fora: 66.7%",
      "risk_note": "Ganhamos com 2+ gols totais na partida. BTTS geral médio: 65.0%.",
      "passed_filters": true,
      "filter_rejections": [],
      "stage": "operation",
      "status": "green",
      "final_score": "3x1",
      "pnl": 496.6,
      "resistance_index": 0.0,
      "recommended_odd": 1.42,
      "league_avg_goals": 2.63,
      "league_edge_pct": 44.1,
      "fair_odd": 1.48,
      "prob_lose_pct": 67.43,
      "fair_note": "xG 1.73/0.87 | calibrado c/ O2.5 | Poisson P(Over 1.5) | mercado Over 1.5 proxy → 58.1% | P(Over 1.5) | blend 55/45",
      "manual_odd": 1.52,
      "lay_stake": 1000.0,
      "lay_profit_green": 496.6,
      "lay_loss_red": -1000.0,
      "ev_pct": 2.49
    },
    {
      "fixture_id": 1512627,
      "strategy": "lay_zebra",
      "league": "Primera División",
      "league_id": 281,
      "league_country": "Peru",
      "league_logo": "https://media.api-sports.io/football/leagues/281.png",
      "date": "2026-05-31",
      "time": "13:00",
      "venue": "Estadio de la UNSA",
      "home_team": "FBC Melgar",
      "home_team_id": 2554,
      "home_team_logo": "https://media.api-sports.io/football/teams/2554.png",
      "away_team": "Alianza Atletico",
      "away_team_id": 2560,
      "away_team_logo": "https://media.api-sports.io/football/teams/2560.png",
      "favorite_side": "home",
      "favorite": "FBC Melgar",
      "underdog": "Alianza Atletico",
      "odds": {
        "home_win": 1.534615384615385,
        "draw": 3.8215384615384616,
        "away_win": 5.836923076923076,
        "score_1x0": 5.565454545454545,
        "score_0x1": 12.402,
        "over25": 1.95,
        "btts_yes": 1.988,
        "prob_1x0": 18.0,
        "prob_0x1": 8.1,
        "short_score_risk": 26.0,
        "favorite_odd": 1.534615384615385,
        "best_goleada_odd": 10.166363636363636
      },
      "home_stats": {
        "rank": 7,
        "goals_avg": 1.8,
        "goals_conceded_avg": 1.1,
        "over25_pct": 50.0,
        "btts_pct": 80.0,
        "draw_pct": 30.0,
        "form": "WDWDW",
        "offensive_strength": 1.38,
        "defensive_fragility": 0.85,
        "avg_shots_on_goal": 6.6,
        "avg_possession": 57.6,
        "avg_corners": 5.6,
        "pressure_index": 100,
        "win_pct": 50.0
      },
      "away_stats": {
        "rank": 10,
        "goals_avg": 1.1,
        "goals_conceded_avg": 1.4,
        "over25_pct": 40.0,
        "btts_pct": 50.0,
        "draw_pct": 20.0,
        "form": "LLDDW",
        "offensive_strength": 0.85,
        "defensive_fragility": 1.08,
        "avg_shots_on_goal": 4.4,
        "avg_possession": 46.4,
        "avg_corners": 2.8,
        "pressure_index": 49.2,
        "win_pct": 30.0
      },
      "score": 70.9,
      "score_class": "BOA",
      "market": "LAY ZEBRA",
      "justification": "Análise: FBC Melgar em boa fase (11/15 pts); Alianza Atletico raramente vence (30% vitórias). Probabilidade de Zebra é baixa.",
      "risk_note": "Lembre-se: Ganhamos no Empate ou Vitória do Favorito. Perigo apenas se a Zebra vencer.",
      "passed_filters": true,
      "filter_rejections": [],
      "stage": "operation",
      "status": "green",
      "final_score": "3x1",
      "pnl": 129.05,
      "resistance_index": 0.0,
      "fair_odd": 13.31,
      "prob_lose_pct": 7.52,
      "fair_note": "xG 1.73/0.87 | calibrado c/ O2.5 | P(avg 1x0/0x1) | mercado score_0x1 → 7.0% | blend 55/45",
      "manual_odd": 8.4,
      "lay_stake": 135.14,
      "lay_profit_green": 129.05,
      "lay_loss_red": -1000.0,
      "ev_pct": 36.83
    },
    {
      "fixture_id": 1512627,
      "strategy": "back_favorito",
      "league": "Primera División",
      "league_id": 281,
      "league_country": "Peru",
      "league_logo": "https://media.api-sports.io/football/leagues/281.png",
      "date": "2026-05-31",
      "time": "13:00",
      "venue": "Estadio de la UNSA",
      "home_team": "FBC Melgar",
      "home_team_id": 2554,
      "home_team_logo": "https://media.api-sports.io/football/teams/2554.png",
      "away_team": "Alianza Atletico",
      "away_team_id": 2560,
      "away_team_logo": "https://media.api-sports.io/football/teams/2560.png",
      "favorite_side": "home",
      "favorite": "FBC Melgar",
      "underdog": "Alianza Atletico",
      "odds": {
        "home_win": 1.534615384615385,
        "draw": 3.8215384615384616,
        "away_win": 5.836923076923076,
        "score_1x0": 5.565454545454545,
        "score_0x1": 12.402,
        "over25": 1.95,
        "btts_yes": 1.988,
        "prob_1x0": 18.0,
        "prob_0x1": 8.1,
        "short_score_risk": 26.0,
        "favorite_odd": 1.534615384615385,
        "best_goleada_odd": 10.166363636363636
      },
      "home_stats": {
        "rank": 7,
        "goals_avg": 1.8,
        "goals_conceded_avg": 1.1,
        "over25_pct": 50.0,
        "btts_pct": 80.0,
        "draw_pct": 30.0,
        "form": "WDWDW",
        "offensive_strength": 1.38,
        "defensive_fragility": 0.85,
        "avg_shots_on_goal": 6.6,
        "avg_possession": 57.6,
        "avg_corners": 5.6,
        "pressure_index": 100,
        "win_pct": 50.0
      },
      "away_stats": {
        "rank": 10,
        "goals_avg": 1.1,
        "goals_conceded_avg": 1.4,
        "over25_pct": 40.0,
        "btts_pct": 50.0,
        "draw_pct": 20.0,
        "form": "LLDDW",
        "offensive_strength": 0.85,
        "defensive_fragility": 1.08,
        "avg_shots_on_goal": 4.4,
        "avg_possession": 46.4,
        "avg_corners": 2.8,
        "pressure_index": 49.2,
        "win_pct": 30.0
      },
      "score": 70.9,
      "score_class": "BOA",
      "market": "BACK FAVORITO",
      "justification": "FBC Melgar WR 50%, forma WDWDW vs Alianza Atletico WR 30% — odd 1.53",
      "risk_note": "Perde se empate (odd 3.82) ou vitória da zebra. Comissão 4.5% aplicada no green.",
      "passed_filters": true,
      "filter_rejections": [],
      "stage": "operation",
      "status": "green",
      "final_score": "3x1",
      "pnl": 506.15,
      "resistance_index": 0.0,
      "fair_odd": 1.73,
      "prob_lose_pct": 57.85,
      "fair_note": "xG 1.73/0.87 | calibrado c/ O2.5 | mercado 1x2 fav → 60.1% | P(Fav Win) | blend 55/45",
      "manual_odd": 1.53,
      "lay_stake": 1000.0,
      "lay_profit_green": 506.15,
      "lay_loss_red": -1000.0,
      "ev_pct": 11.49
    },
    {
      "fixture_id": 1546801,
      "strategy": "back_btts",
      "league": "Primera División - Apertura",
      "league_id": 268,
      "league_country": "Uruguay",
      "league_logo": "https://media.api-sports.io/football/leagues/268.png",
      "date": "2026-05-31",
      "time": "15:00",
      "venue": "Parque Artigas",
      "home_team": "Juventud",
      "home_team_id": 2353,
      "home_team_logo": "https://media.api-sports.io/football/teams/2353.png",
      "away_team": "Wanderers",
      "away_team_id": 2360,
      "away_team_logo": "https://media.api-sports.io/football/teams/2360.png",
      "favorite_side": "home",
      "favorite": "Juventud",
      "underdog": "Wanderers",
      "odds": {
        "home_win": 2.221538461538462,
        "draw": 3.1623076923076923,
        "away_win": 3.08,
        "score_1x0": 6.416363636363636,
        "score_0x1": 7.937,
        "over25": 2.1130000000000004,
        "btts_yes": 1.8199999999999998,
        "prob_1x0": 15.6,
        "prob_0x1": 12.6,
        "short_score_risk": 28.2,
        "favorite_odd": 2.221538461538462,
        "best_goleada_odd": 17.385454545454547
      },
      "home_stats": {
        "rank": 2,
        "goals_avg": 1.8,
        "goals_conceded_avg": 1.4,
        "over25_pct": 60.0,
        "over15_pct": 100.0,
        "goals_scored_home_avg": 2.1666666666666665,
        "goals_scored_away_avg": 1.25,
        "goals_conceded_home_avg": 1.5,
        "goals_conceded_away_avg": 1.25,
        "scored_in_home_pct": 100.0,
        "scored_in_away_pct": 100.0,
        "conceded_in_home_pct": 66.66666666666666,
        "conceded_in_away_pct": 100.0,
        "over15_home_pct": 100.0,
        "over15_away_pct": 100.0,
        "btts_pct": 80.0,
        "draw_pct": 40.0,
        "form": "LLDDW",
        "offensive_strength": 1.38,
        "defensive_fragility": 1.08,
        "avg_shots_on_goal": 3.5,
        "avg_possession": 54.5,
        "avg_corners": 5.5,
        "pressure_index": 69.0,
        "win_pct": 40.0
      },
      "away_stats": {
        "rank": 3,
        "goals_avg": 1.2,
        "goals_conceded_avg": 1.3,
        "over25_pct": 50.0,
        "over15_pct": 60.0,
        "goals_scored_home_avg": 0.8,
        "goals_scored_away_avg": 1.6,
        "goals_conceded_home_avg": 0.6,
        "goals_conceded_away_avg": 2.0,
        "scored_in_home_pct": 80.0,
        "scored_in_away_pct": 80.0,
        "conceded_in_home_pct": 40.0,
        "conceded_in_away_pct": 80.0,
        "over15_home_pct": 40.0,
        "over15_away_pct": 80.0,
        "btts_pct": 60.0,
        "draw_pct": 30.0,
        "form": "DWDDW",
        "offensive_strength": 0.92,
        "defensive_fragility": 1.0,
        "avg_shots_on_goal": 0.0,
        "avg_possession": 0.0,
        "avg_corners": 0.0,
        "pressure_index": 0.0,
        "win_pct": 30.0
      },
      "score": 74.3,
      "score_class": "BOA",
      "market": "BACK BTTS",
      "justification": "BTTS médio 70%; Juventud marca em casa 100%, Wanderers marca fora 80%; odd BTTS 1.82",
      "risk_note": "Perde se qualquer time zerar. Casa sofre em casa 67%, Fora sofre fora 80%.",
      "passed_filters": true,
      "filter_rejections": [],
      "stage": "rejected_by_odd",
      "status": "pending",
      "final_score": "",
      "pnl": 0.0,
      "resistance_index": 0.0,
      "recommended_odd": 0.0,
      "league_avg_goals": 0.0,
      "league_edge_pct": 0.0,
      "fair_odd": 1.97,
      "prob_lose_pct": 50.84,
      "fair_note": "xG 1.49/0.97 | calibrado c/ O2.5 | Poisson+DC P(BTTS) | mercado BTTS Sim → 51.8% | P(BTTS Sim) | blend 55/45",
      "manual_odd": 50.0,
      "reject_reason": "Odd Lay muito alta para back_btts (50.0 > 25.0)",
      "ev_pct": 2442.0
    },
    {
      "fixture_id": 1547754,
      "strategy": "lay_0x1_zebra",
      "league": "I Liga",
      "league_id": 107,
      "league_country": "Poland",
      "league_logo": "https://media.api-sports.io/football/leagues/107.png",
      "date": "2026-05-31",
      "time": "15:45",
      "venue": "Stadion KS Wieczysta",
      "home_team": "Wieczysta Kraków",
      "home_team_id": 17115,
      "home_team_logo": "https://media.api-sports.io/football/teams/17115.png",
      "away_team": "Chrobry Głogów",
      "away_team_id": 3483,
      "away_team_logo": "https://media.api-sports.io/football/teams/3483.png",
      "favorite_side": "home",
      "favorite": "Wieczysta Kraków",
      "underdog": "Chrobry Głogów",
      "odds": {
        "home_win": 1.653333333333333,
        "draw": 3.7950000000000004,
        "away_win": 4.383333333333334,
        "score_1x0": 7.614,
        "score_0x1": 13.4,
        "over25": 1.61,
        "btts_yes": 1.5999999999999999,
        "prob_1x0": 13.1,
        "prob_0x1": 7.5,
        "short_score_risk": 20.6,
        "favorite_odd": 1.653333333333333,
        "best_goleada_odd": 10.678999999999998
      },
      "home_stats": {
        "rank": 3,
        "goals_avg": 2.3,
        "goals_conceded_avg": 1.0,
        "over25_pct": 50.0,
        "btts_pct": 60.0,
        "draw_pct": 20.0,
        "form": "WWDWL",
        "offensive_strength": 1.77,
        "defensive_fragility": 0.77,
        "avg_shots_on_goal": 0.0,
        "avg_possession": 0.0,
        "avg_corners": 0.0,
        "pressure_index": 0.0,
        "win_pct": 70.0
      },
      "away_stats": {
        "rank": 4,
        "goals_avg": 1.3,
        "goals_conceded_avg": 1.4,
        "over25_pct": 50.0,
        "btts_pct": 70.0,
        "draw_pct": 20.0,
        "form": "LDWLW",
        "offensive_strength": 1.0,
        "defensive_fragility": 1.08,
        "avg_shots_on_goal": 0.0,
        "avg_possession": 0.0,
        "avg_corners": 0.0,
        "pressure_index": 0.0,
        "win_pct": 40.0
      },
      "score": 68.2,
      "score_class": "BOA",
      "market": "LAY 0x1",
      "justification": "Wieczysta Kraków ataque 2.3, sofridos 1.0 — Chrobry Głogów ataque fraco 1.3",
      "risk_note": "Lembre-se: Ganhamos se o favorito marcar ou se o jogo empatar/zebra não fizer 0x1. Odd limite do Lay: 20.0.",
      "passed_filters": true,
      "filter_rejections": [],
      "stage": "rejected_by_odd",
      "pnl": 0,
      "resistance_index": 0.0,
      "fair_odd": 16.28,
      "prob_lose_pct": 6.14,
      "fair_note": "xG 2.11/0.93 | calibrado c/ O2.5 | P(avg 1x0/0x1) | mercado score_0x1 → 6.5% | blend 55/45",
      "manual_odd": 50.0,
      "reject_reason": "Odd Lay muito alta para lay_0x1_zebra (50.0 > 20.0)",
      "ev_pct": -207.0
    },
    {
      "fixture_id": 1537993,
      "strategy": "lay_zebrao",
      "league": "Serie D",
      "league_id": 76,
      "league_country": "Brazil",
      "league_logo": "https://media.api-sports.io/football/leagues/76.png",
      "date": "2026-05-31",
      "time": "16:00",
      "venue": null,
      "home_team": "CSA",
      "home_team_id": 150,
      "home_team_logo": "https://media.api-sports.io/football/teams/150.png",
      "away_team": "Jacuipense",
      "away_team_id": 7831,
      "away_team_logo": "https://media.api-sports.io/football/teams/7831.png",
      "favorite_side": "home",
      "favorite": "CSA",
      "underdog": "Jacuipense",
      "odds": {
        "home_win": 1.3372727272727274,
        "draw": 4.05,
        "away_win": 8.42181818181818,
        "score_1x0": 4.94375,
        "score_0x1": 15.34375,
        "over25": 1.92625,
        "btts_yes": 2.2671428571428573,
        "prob_1x0": 20.2,
        "prob_0x1": 6.5,
        "short_score_risk": 26.7,
        "favorite_odd": 1.3372727272727274,
        "best_goleada_odd": 7.31875
      },
      "home_stats": {
        "rank": null,
        "goals_avg": 2.1,
        "goals_conceded_avg": 0.9,
        "over25_pct": 50.0,
        "btts_pct": 70.0,
        "draw_pct": 30.0,
        "form": "DDWWW",
        "offensive_strength": 1.62,
        "defensive_fragility": 0.69,
        "avg_shots_on_goal": 0.0,
        "avg_possession": 0.0,
        "avg_corners": 0.0,
        "pressure_index": 0.0,
        "win_pct": 60.0
      },
      "away_stats": {
        "rank": null,
        "goals_avg": 1.1,
        "goals_conceded_avg": 1.8,
        "over25_pct": 60.0,
        "btts_pct": 60.0,
        "draw_pct": 20.0,
        "form": "DDWLW",
        "offensive_strength": 0.85,
        "defensive_fragility": 1.38,
        "avg_shots_on_goal": 1.0,
        "avg_possession": 33.0,
        "avg_corners": 2.0,
        "pressure_index": 0,
        "win_pct": 30.0
      },
      "score": 77.0,
      "score_class": "FORTE",
      "market": "LAY ZEBRÃO",
      "justification": "CSA ataque 2.1, Over2.5 50% — zebra (Jacuipense) odd 8.42, sofre 1.8/j",
      "risk_note": "Operação in-play: sair em 0-0 HT, gol da zebra ou red. Seguir se favorito marcar primeiro. PnL informado manualmente.",
      "passed_filters": true,
      "filter_rejections": [],
      "stage": "operation",
      "status": "breakeven",
      "final_score": "manual",
      "pnl": 0.0,
      "resistance_index": 0.0,
      "lay_stake": 1000.0,
      "fair_odd": 14.33,
      "prob_lose_pct": 6.98,
      "fair_note": "xG 1.97/0.66 | calibrado c/ O2.5 | P(avg 1x0/0x1) | mercado score_0x1 → 5.7% | blend 55/45",
      "manual_pnl": 0.0
    },
    {
      "fixture_id": 1526840,
      "strategy": "back_favorito",
      "league": "Serie C",
      "league_id": 75,
      "league_country": "Brazil",
      "league_logo": "https://media.api-sports.io/football/leagues/75.png",
      "date": "2026-05-31",
      "time": "16:00",
      "venue": null,
      "home_team": "Guarani Campinas",
      "home_team_id": 138,
      "home_team_logo": "https://media.api-sports.io/football/teams/138.png",
      "away_team": "Amazonas",
      "away_team_id": 10862,
      "away_team_logo": "https://media.api-sports.io/football/teams/10862.png",
      "favorite_side": "home",
      "favorite": "Guarani Campinas",
      "underdog": "Amazonas",
      "odds": {
        "home_win": 1.586666666666667,
        "draw": 3.486666666666667,
        "away_win": 5.534166666666668,
        "score_1x0": 5.142,
        "score_0x1": 10.933,
        "over25": 2.1244444444444444,
        "btts_yes": 2.0888888888888886,
        "prob_1x0": 19.4,
        "prob_0x1": 9.1,
        "short_score_risk": 28.6,
        "favorite_odd": 1.586666666666667,
        "best_goleada_odd": 10.636
      },
      "home_stats": {
        "rank": 7,
        "goals_avg": 2.1,
        "goals_conceded_avg": 0.8,
        "over25_pct": 40.0,
        "btts_pct": 50.0,
        "draw_pct": 40.0,
        "form": "WWLWW",
        "offensive_strength": 1.62,
        "defensive_fragility": 0.62,
        "avg_shots_on_goal": 0.0,
        "avg_possession": 0.0,
        "avg_corners": 0.0,
        "pressure_index": 0.0,
        "win_pct": 50.0
      },
      "away_stats": {
        "rank": null,
        "goals_avg": 1.4,
        "goals_conceded_avg": 1.5,
        "over25_pct": 60.0,
        "btts_pct": 50.0,
        "draw_pct": 20.0,
        "form": "LLLLD",
        "offensive_strength": 1.08,
        "defensive_fragility": 1.15,
        "avg_shots_on_goal": 0.0,
        "avg_possession": 0.0,
        "avg_corners": 0.0,
        "pressure_index": 0.0,
        "win_pct": 40.0
      },
      "score": 75.1,
      "score_class": "FORTE",
      "market": "BACK FAVORITO",
      "justification": "Guarani Campinas WR 50%, forma WWLWW vs Amazonas WR 40% — odd 1.59",
      "risk_note": "Perde se empate (odd 3.49) ou vitória da zebra. Comissão 4.5% aplicada no green.",
      "passed_filters": true,
      "filter_rejections": [],
      "stage": "operation",
      "status": "green",
      "final_score": "5x0",
      "pnl": 487.05,
      "resistance_index": 0.0,
      "fair_odd": 1.71,
      "prob_lose_pct": 58.62,
      "fair_note": "xG 1.72/0.73 | calibrado c/ O2.5 | mercado 1x2 fav → 57.4% | P(Fav Win) | blend 55/45",
      "manual_odd": 1.51,
      "lay_stake": 1000.0,
      "lay_profit_green": 487.05,
      "lay_loss_red": -1000.0,
      "ev_pct": 11.48
    },
    {
      "fixture_id": 1537993,
      "strategy": "over_15",
      "league": "Serie D",
      "league_id": 76,
      "league_country": "Brazil",
      "league_logo": "https://media.api-sports.io/football/leagues/76.png",
      "date": "2026-05-31",
      "time": "16:00",
      "venue": null,
      "home_team": "CSA",
      "home_team_id": 150,
      "home_team_logo": "https://media.api-sports.io/football/teams/150.png",
      "away_team": "Jacuipense",
      "away_team_id": 7831,
      "away_team_logo": "https://media.api-sports.io/football/teams/7831.png",
      "favorite_side": "home",
      "favorite": "CSA",
      "underdog": "Jacuipense",
      "odds": {
        "home_win": 1.3372727272727274,
        "draw": 4.05,
        "away_win": 8.42181818181818,
        "score_1x0": 4.94375,
        "score_0x1": 15.34375,
        "over25": 1.92625,
        "btts_yes": 2.2671428571428573,
        "prob_1x0": 20.2,
        "prob_0x1": 6.5,
        "short_score_risk": 26.7,
        "favorite_odd": 1.3372727272727274,
        "best_goleada_odd": 7.31875
      },
      "home_stats": {
        "rank": null,
        "goals_avg": 2.1,
        "goals_conceded_avg": 0.9,
        "over25_pct": 50.0,
        "over15_pct": 90.0,
        "goals_scored_home_avg": 1.6,
        "goals_scored_away_avg": 2.6,
        "goals_conceded_home_avg": 0.6,
        "goals_conceded_away_avg": 1.2,
        "scored_in_home_pct": 100.0,
        "scored_in_away_pct": 100.0,
        "conceded_in_home_pct": 60.0,
        "conceded_in_away_pct": 80.0,
        "over15_home_pct": 100.0,
        "over15_away_pct": 80.0,
        "btts_pct": 70.0,
        "draw_pct": 30.0,
        "form": "DDWWW",
        "offensive_strength": 1.62,
        "defensive_fragility": 0.69,
        "avg_shots_on_goal": 0.0,
        "avg_possession": 0.0,
        "avg_corners": 0.0,
        "pressure_index": 0.0,
        "win_pct": 60.0
      },
      "away_stats": {
        "rank": null,
        "goals_avg": 1.1,
        "goals_conceded_avg": 1.8,
        "over25_pct": 60.0,
        "over15_pct": 70.0,
        "goals_scored_home_avg": 1.2,
        "goals_scored_away_avg": 1.0,
        "goals_conceded_home_avg": 1.6,
        "goals_conceded_away_avg": 2.0,
        "scored_in_home_pct": 80.0,
        "scored_in_away_pct": 80.0,
        "conceded_in_home_pct": 80.0,
        "conceded_in_away_pct": 80.0,
        "over15_home_pct": 60.0,
        "over15_away_pct": 80.0,
        "btts_pct": 60.0,
        "draw_pct": 20.0,
        "form": "DDWLW",
        "offensive_strength": 0.85,
        "defensive_fragility": 1.38,
        "avg_shots_on_goal": 1.0,
        "avg_possession": 33.0,
        "avg_corners": 2.0,
        "pressure_index": 0,
        "win_pct": 30.0
      },
      "score": 74.8,
      "score_class": "BOA",
      "market": "OVER 1.5",
      "justification": "Média Gols: 3.20; Over 1.5 geral médio: 80.0%; Casa marca em casa: 100.0%; Fora marca fora: 80.0%",
      "risk_note": "Ganhamos com 2+ gols totais na partida. BTTS geral médio: 65.0%.",
      "passed_filters": true,
      "filter_rejections": [],
      "stage": "rejected_by_odd",
      "status": "pending",
      "final_score": "",
      "pnl": 0.0,
      "resistance_index": 0.0,
      "recommended_odd": 1.57,
      "league_avg_goals": 2.3,
      "league_edge_pct": 28.9,
      "fair_odd": 1.47,
      "prob_lose_pct": 67.86,
      "fair_note": "xG 1.97/0.66 | calibrado c/ O2.5 | Poisson P(Over 1.5) | mercado Over 1.5 proxy → 58.8% | P(Over 1.5) | blend 55/45",
      "manual_odd": 50.0,
      "reject_reason": "Odd Lay muito alta para over_15 (50.0 > 25.0)",
      "ev_pct": 3293.0
    },
    {
      "fixture_id": 1526841,
      "strategy": "over_15",
      "league": "Serie C",
      "league_id": 75,
      "league_country": "Brazil",
      "league_logo": "https://media.api-sports.io/football/leagues/75.png",
      "date": "2026-05-31",
      "time": "16:00",
      "venue": null,
      "home_team": "Inter De Limeira",
      "home_team_id": 1201,
      "home_team_logo": "https://media.api-sports.io/football/teams/1201.png",
      "away_team": "Ypiranga-RS",
      "away_team_id": 1221,
      "away_team_logo": "https://media.api-sports.io/football/teams/1221.png",
      "favorite_side": "home",
      "favorite": "Inter De Limeira",
      "underdog": "Ypiranga-RS",
      "odds": {
        "home_win": 1.8891666666666669,
        "draw": 3.054166666666667,
        "away_win": 4.051666666666667,
        "score_1x0": 5.169,
        "score_0x1": 8.440999999999999,
        "over25": 2.321111111111111,
        "btts_yes": 2.042222222222222,
        "prob_1x0": 19.3,
        "prob_0x1": 11.8,
        "short_score_risk": 31.2,
        "favorite_odd": 1.8891666666666669,
        "best_goleada_odd": 14.134
      },
      "home_stats": {
        "rank": null,
        "goals_avg": 1.2,
        "goals_conceded_avg": 1.1,
        "over25_pct": 60.0,
        "over15_pct": 70.0,
        "goals_scored_home_avg": 1.0,
        "goals_scored_away_avg": 1.5,
        "goals_conceded_home_avg": 1.3333333333333333,
        "goals_conceded_away_avg": 0.75,
        "scored_in_home_pct": 83.33333333333334,
        "scored_in_away_pct": 100.0,
        "conceded_in_home_pct": 83.33333333333334,
        "conceded_in_away_pct": 50.0,
        "over15_home_pct": 83.33333333333334,
        "over15_away_pct": 50.0,
        "btts_pct": 70.0,
        "draw_pct": 30.0,
        "form": "WDWLW",
        "offensive_strength": 0.92,
        "defensive_fragility": 0.85,
        "avg_shots_on_goal": 0.0,
        "avg_possession": 0.0,
        "avg_corners": 0.0,
        "pressure_index": 0.0,
        "win_pct": 40.0
      },
      "away_stats": {
        "rank": 10,
        "goals_avg": 1.4,
        "goals_conceded_avg": 1.5,
        "over25_pct": 70.0,
        "over15_pct": 100.0,
        "goals_scored_home_avg": 1.75,
        "goals_scored_away_avg": 1.1666666666666667,
        "goals_conceded_home_avg": 1.25,
        "goals_conceded_away_avg": 1.6666666666666667,
        "scored_in_home_pct": 100.0,
        "scored_in_away_pct": 83.33333333333334,
        "conceded_in_home_pct": 50.0,
        "conceded_in_away_pct": 83.33333333333334,
        "over15_home_pct": 100.0,
        "over15_away_pct": 100.0,
        "btts_pct": 60.0,
        "draw_pct": 10.0,
        "form": "LLLLW",
        "offensive_strength": 1.08,
        "defensive_fragility": 1.15,
        "avg_shots_on_goal": 0.0,
        "avg_possession": 0.0,
        "avg_corners": 0.0,
        "pressure_index": 0.0,
        "win_pct": 40.0
      },
      "score": 70.6,
      "score_class": "BOA",
      "market": "OVER 1.5",
      "justification": "Média Gols: 2.60; Over 1.5 geral médio: 85.0%; Casa marca em casa: 83.3%; Fora marca fora: 83.3%",
      "risk_note": "Ganhamos com 2+ gols totais na partida. BTTS geral médio: 65.0%.",
      "passed_filters": true,
      "filter_rejections": [],
      "stage": "rejected_by_odd",
      "status": "pending",
      "final_score": "",
      "pnl": 0.0,
      "resistance_index": 0.0,
      "recommended_odd": 1.76,
      "league_avg_goals": 2.01,
      "league_edge_pct": 38.5,
      "fair_odd": 1.67,
      "prob_lose_pct": 59.94,
      "fair_note": "xG 1.33/0.98 | calibrado c/ O2.5 | Poisson P(Over 1.5) | mercado Over 1.5 proxy → 48.8% | P(Over 1.5) | blend 55/45",
      "manual_odd": 50.0,
      "reject_reason": "Odd Lay muito alta para over_15 (50.0 > 25.0)",
      "ev_pct": 2897.0
    },
    {
      "fixture_id": 1526840,
      "strategy": "lay_empate",
      "league": "Serie C",
      "league_id": 75,
      "league_country": "Brazil",
      "league_logo": "https://media.api-sports.io/football/leagues/75.png",
      "date": "2026-05-31",
      "time": "16:00",
      "venue": null,
      "home_team": "Guarani Campinas",
      "home_team_id": 138,
      "home_team_logo": "https://media.api-sports.io/football/teams/138.png",
      "away_team": "Amazonas",
      "away_team_id": 10862,
      "away_team_logo": "https://media.api-sports.io/football/teams/10862.png",
      "favorite_side": "home",
      "favorite": "Guarani Campinas",
      "underdog": "Amazonas",
      "odds": {
        "home_win": 1.586666666666667,
        "draw": 3.486666666666667,
        "away_win": 5.534166666666668,
        "score_1x0": 5.142,
        "score_0x1": 10.933,
        "over25": 2.1244444444444444,
        "btts_yes": 2.0888888888888886,
        "prob_1x0": 19.4,
        "prob_0x1": 9.1,
        "short_score_risk": 28.6,
        "favorite_odd": 1.586666666666667,
        "best_goleada_odd": 10.636
      },
      "home_stats": {
        "rank": 7,
        "goals_avg": 2.1,
        "goals_conceded_avg": 0.8,
        "over25_pct": 40.0,
        "btts_pct": 50.0,
        "draw_pct": 40.0,
        "form": "WWLWW",
        "offensive_strength": 1.62,
        "defensive_fragility": 0.62,
        "avg_shots_on_goal": 0.0,
        "avg_possession": 0.0,
        "avg_corners": 0.0,
        "pressure_index": 0.0,
        "win_pct": 50.0
      },
      "away_stats": {
        "rank": null,
        "goals_avg": 1.4,
        "goals_conceded_avg": 1.5,
        "over25_pct": 60.0,
        "btts_pct": 50.0,
        "draw_pct": 20.0,
        "form": "LLLLD",
        "offensive_strength": 1.08,
        "defensive_fragility": 1.15,
        "avg_shots_on_goal": 0.0,
        "avg_possession": 0.0,
        "avg_corners": 0.0,
        "pressure_index": 0.0,
        "win_pct": 40.0
      },
      "score": 68.3,
      "score_class": "BOA",
      "market": "LAY EMPATE",
      "justification": "Jogo ofensivo (média combinada 3.5 gols/j); favorito claro (odd 1.59)",
      "risk_note": "Risco se jogo travar em 0x0/1x1 — odd empate 3.49",
      "passed_filters": true,
      "filter_rejections": [],
      "stage": "operation",
      "status": "green",
      "final_score": "5x0",
      "pnl": 265.28,
      "resistance_index": 0.0,
      "fair_odd": 3.79,
      "prob_lose_pct": 26.37,
      "fair_note": "xG 1.72/0.73 | calibrado c/ O2.5 | Poisson+DC P(empate) | mercado devig 1x2 → 26.1% | blend 55/45",
      "manual_odd": 4.6,
      "lay_stake": 277.78,
      "lay_profit_green": 265.28,
      "lay_loss_red": -1000.0,
      "ev_pct": -21.3
    },
    {
      "fixture_id": 1492286,
      "strategy": "lay_zebra",
      "league": "Serie A",
      "league_id": 71,
      "league_country": "Brazil",
      "league_logo": "https://media.api-sports.io/football/leagues/71.png",
      "date": "2026-05-31",
      "time": "16:00",
      "venue": "Nubank Parque",
      "home_team": "Palmeiras",
      "home_team_id": 121,
      "home_team_logo": "https://media.api-sports.io/football/teams/121.png",
      "away_team": "Chapecoense-sc",
      "away_team_id": 132,
      "away_team_logo": "https://media.api-sports.io/football/teams/132.png",
      "favorite_side": "home",
      "favorite": "Palmeiras",
      "underdog": "Chapecoense-sc",
      "odds": {
        "home_win": 1.3369230769230769,
        "draw": 5.0346153846153845,
        "away_win": 8.73846153846154,
        "score_1x0": 6.512727272727273,
        "score_0x1": 19.624000000000002,
        "over25": 1.6909090909090911,
        "btts_yes": 1.9899999999999998,
        "prob_1x0": 15.4,
        "prob_0x1": 5.1,
        "short_score_risk": 20.5,
        "favorite_odd": 1.3369230769230769,
        "best_goleada_odd": 7.975454545454546
      },
      "home_stats": {
        "rank": 2,
        "goals_avg": 1.8,
        "goals_conceded_avg": 0.7,
        "over25_pct": 30.0,
        "btts_pct": 60.0,
        "draw_pct": 40.0,
        "form": "WWWLD",
        "offensive_strength": 1.38,
        "defensive_fragility": 0.54,
        "avg_shots_on_goal": 5.0,
        "avg_possession": 54.0,
        "avg_corners": 3.8,
        "pressure_index": 73.2,
        "win_pct": 50.0
      },
      "away_stats": {
        "rank": null,
        "goals_avg": 1.5,
        "goals_conceded_avg": 1.3,
        "over25_pct": 60.0,
        "btts_pct": 70.0,
        "draw_pct": 20.0,
        "form": "LDLWL",
        "offensive_strength": 1.15,
        "defensive_fragility": 1.0,
        "avg_shots_on_goal": 5.0,
        "avg_possession": 46.0,
        "avg_corners": 2.3,
        "pressure_index": 51.3,
        "win_pct": 40.0
      },
      "score": 66.7,
      "score_class": "BOA",
      "market": "LAY ZEBRA",
      "justification": "Análise: Palmeiras em boa fase (10/15 pts); Chapecoense-sc raramente vence (40% vitórias). Probabilidade de Zebra é baixa.",
      "risk_note": "Lembre-se: Ganhamos no Empate ou Vitória do Favorito. Perigo apenas se a Zebra vencer.",
      "passed_filters": true,
      "filter_rejections": [],
      "stage": "operation",
      "status": "green",
      "final_score": "1x0",
      "pnl": 116.46,
      "resistance_index": 0.0,
      "fair_odd": 18.23,
      "prob_lose_pct": 5.49,
      "fair_note": "xG 1.93/0.98 | calibrado c/ O2.5 | P(avg 1x0/0x1) | mercado score_0x1 → 4.4% | blend 55/45",
      "manual_odd": 9.2,
      "lay_stake": 121.95,
      "lay_profit_green": 116.46,
      "lay_loss_red": -1000.0,
      "ev_pct": 49.49
    },
    {
      "fixture_id": 1519378,
      "strategy": "back_favorito",
      "league": "Liga Pro",
      "league_id": 242,
      "league_country": "Ecuador",
      "league_logo": "https://media.api-sports.io/football/leagues/242.png",
      "date": "2026-05-31",
      "time": "17:30",
      "venue": "Estadio Christian Benitez Betancourt",
      "home_team": "Guayaquil City FC",
      "home_team_id": 1159,
      "home_team_logo": "https://media.api-sports.io/football/teams/1159.png",
      "away_team": "Independiente del Valle",
      "away_team_id": 1153,
      "away_team_logo": "https://media.api-sports.io/football/teams/1153.png",
      "favorite_side": "away",
      "favorite": "Independiente del Valle",
      "underdog": "Guayaquil City FC",
      "odds": {
        "home_win": 4.945384615384615,
        "draw": 3.4407692307692304,
        "away_win": 1.643076923076923,
        "score_1x0": 10.986363636363636,
        "score_0x1": 5.522,
        "over25": 2.021,
        "btts_yes": 1.9289999999999998,
        "prob_1x0": 9.1,
        "prob_0x1": 18.1,
        "short_score_risk": 27.2,
        "favorite_odd": 1.643076923076923,
        "best_goleada_odd": 11.55
      },
      "home_stats": {
        "rank": null,
        "goals_avg": 1.2,
        "goals_conceded_avg": 1.3,
        "over25_pct": 50.0,
        "btts_pct": 50.0,
        "draw_pct": 10.0,
        "form": "LDLLL",
        "offensive_strength": 0.92,
        "defensive_fragility": 1.0,
        "avg_shots_on_goal": 3.5,
        "avg_possession": 54.0,
        "avg_corners": 2.5,
        "pressure_index": 56.0,
        "win_pct": 40.0
      },
      "away_stats": {
        "rank": 1,
        "goals_avg": 2.4,
        "goals_conceded_avg": 1.2,
        "over25_pct": 70.0,
        "btts_pct": 50.0,
        "draw_pct": 0.0,
        "form": "WWLWW",
        "offensive_strength": 1.85,
        "defensive_fragility": 0.92,
        "avg_shots_on_goal": 8.6,
        "avg_possession": 57.4,
        "avg_corners": 8.0,
        "pressure_index": 100,
        "win_pct": 80.0
      },
      "score": 58.0,
      "score_class": "REGULAR",
      "market": "BACK FAVORITO",
      "justification": "Independiente del Valle WR 80%, forma WWLWW vs Guayaquil City FC WR 40% — odd 1.64",
      "risk_note": "Perde se empate (odd 3.44) ou vitória da zebra. Comissão 4.5% aplicada no green.",
      "passed_filters": true,
      "filter_rejections": [],
      "stage": "operation",
      "status": "green",
      "final_score": "2x4",
      "pnl": 668.5,
      "resistance_index": 0.0,
      "fair_odd": 2.01,
      "prob_lose_pct": 49.83,
      "fair_note": "xG 1.05/1.49 | calibrado c/ O2.5 | mercado 1x2 fav → 55.3% | P(Fav Win) | blend 55/45",
      "manual_odd": 1.7,
      "lay_stake": 1000.0,
      "lay_profit_green": 668.5,
      "lay_loss_red": -1000.0,
      "ev_pct": 15.29
    },
    {
      "fixture_id": 1492283,
      "strategy": "lay_0x1_zebra",
      "league": "Serie A",
      "league_id": 71,
      "league_country": "Brazil",
      "league_logo": "https://media.api-sports.io/football/leagues/71.png",
      "date": "2026-05-31",
      "time": "20:30",
      "venue": "Governador Magalhães Pinto",
      "home_team": "Cruzeiro",
      "home_team_id": 135,
      "home_team_logo": "https://media.api-sports.io/football/teams/135.png",
      "away_team": "Fluminense",
      "away_team_id": 124,
      "away_team_logo": "https://media.api-sports.io/football/teams/124.png",
      "favorite_side": "home",
      "favorite": "Cruzeiro",
      "underdog": "Fluminense",
      "odds": {
        "home_win": 1.9030769230769233,
        "draw": 3.3799999999999994,
        "away_win": 4.1438461538461535,
        "score_1x0": 6.385454545454547,
        "score_0x1": 10.062000000000001,
        "over25": 2.0336363636363637,
        "btts_yes": 1.842,
        "prob_1x0": 15.7,
        "prob_0x1": 9.9,
        "short_score_risk": 25.6,
        "favorite_odd": 1.9030769230769233,
        "best_goleada_odd": 14.67090909090909
      },
      "home_stats": {
        "rank": 3,
        "goals_avg": 1.4,
        "goals_conceded_avg": 0.8,
        "over25_pct": 40.0,
        "btts_pct": 60.0,
        "draw_pct": 40.0,
        "form": "DWWDD",
        "offensive_strength": 1.08,
        "defensive_fragility": 0.62,
        "avg_shots_on_goal": 5.0,
        "avg_possession": 57.0,
        "avg_corners": 5.2,
        "pressure_index": 84.8,
        "win_pct": 50.0
      },
      "away_stats": {
        "rank": 5,
        "goals_avg": 1.3,
        "goals_conceded_avg": 1.3,
        "over25_pct": 50.0,
        "btts_pct": 70.0,
        "draw_pct": 30.0,
        "form": "DWLWW",
        "offensive_strength": 1.0,
        "defensive_fragility": 1.0,
        "avg_shots_on_goal": 4.0,
        "avg_possession": 57.4,
        "avg_corners": 3.8,
        "pressure_index": 72.0,
        "win_pct": 40.0
      },
      "score": 64.0,
      "score_class": "REGULAR",
      "market": "LAY 0x1",
      "justification": "Cruzeiro ataque 1.4, sofridos 0.8 — Fluminense ataque fraco 1.3",
      "risk_note": "Lembre-se: Ganhamos se o favorito marcar ou se o jogo empatar/zebra não fizer 0x1. Odd limite do Lay: 20.0.",
      "passed_filters": true,
      "filter_rejections": [],
      "stage": "pre_filter",
      "pnl": 0,
      "resistance_index": 0.0,
      "fair_odd": 11.83,
      "prob_lose_pct": 8.45,
      "fair_note": "xG 1.60/0.93 | calibrado c/ O2.5 | P(avg 1x0/0x1) | mercado score_0x1 → 8.6% | blend 55/45",
      "manual_pnl": -663.0
    }
  ]
}